Workbook

Sheet Start_Here
A1: Inventory & Procurement Planning Simulation
A2: Portfolio-ready Excel model | Synthetic retail data | No coding required
A4: Project purpose | B4: Analyze stock levels, supplier trade-offs, replenishment needs and estimated procurement costs for a fictional retail business.
A5: Data note | B5: All product, supplier and cost data are synthetic and for educational demonstration only.
A6: Recommended workflow | B6: 1. Review Inventory_Master. 2. Compare Supplier_Comparison. 3. Review Cost_Assumptions. 4. Analyze Replenishment_Plan and Scenario_Analysis. 5. Review Cost_Analysis and Management_Dashboard.
A7: Inventory_Master | B7: 30 SKUs across five categories. Reorder point and inventory value are formula-driven.
A8: Supplier_Comparison | B8: Three supplier quotes per SKU. Supplier scores are normalized within each SKU and weighted.
A9: Cost_Assumptions | B9: Yellow cells are editable assumptions. Change values to test alternative operating conditions.
A10: Replenishment_Plan | B10: Shows reorder status, recommended supplier, MOQ-adjusted order quantity and estimated purchase cost.
A11: Scenario_Analysis | B11: Compares baseline, 30% higher demand, and four additional days of supplier delay.
A12: Cost_Analysis | B12: Estimates annual holding cost, ordering cost and purchase cost. Stockout penalty is an illustrative risk proxy, not a forecast.
A13: Management_Dashboard | B13: Summary KPIs and charts. Excel may need to recalculate formulas when first opened.
A14: Supplier scoring | B14: Price 40%, lead time 25%, defect-rate quality score 20%, on-time delivery 15%. Higher weighted score is preferred.
A15: Model limitations | B15: Demand is assumed stable within each scenario; actual seasonality, supplier capacity, taxes, freight, cash constraints and uncertain lead times are not modeled.
A16: Portfolio deliverables | B16: Workbook, README, analysis report, screenshots. Include findings only after reviewing the calculated workbook results.

Sheet Inventory_Master
A1: Inventory Master
A2: 30 fictional products. Verify formulas before using the workbook for portfolio conclusions.
A3: SKU | B3: Product | C3: Category | D3: Unit Cost (₹) | E3: Current Stock (units) | F3: Avg Daily Demand (units) | G3: Lead Time (days) | H3: Safety Stock (units) | I3: Reorder Point (units) | J3: Inventory Value (₹) | K3: Recommended Supplier | L3: Supplier Unit Price (₹) | M3: Supplier Lead Time (days) | N3: Supplier MOQ (units) | O3: Supplier Score
A4: SKU001 | B4: Wireless Mouse | C4: Electronics | D4: 650 | E4: 74 | F4: 6 | G4: 3 | H4: 24 | I4: =F4*G4+H4 | J4: =D4*E4 | K4: Supplier A | L4: 635.21 | M4: 3 | N4: 10 | O4: 82.256429
A5: SKU002 | B5: USB-C Cable | C5: Electronics | D5: 180 | E5: 165 | F5: 7 | G5: 4 | H5: 14 | I5: =F5*G5+H5 | J5: =D5*E5 | K5: Supplier C | L5: 199.18 | M5: 6 | N5: 25 | O5: 88.700101
A6: SKU003 | B6: Laptop Stand | C6: Electronics | D6: 300 | E6: 35 | F6: 4 | G6: 3 | H6: 8 | I6: =F6*G6+H6 | J6: =D6*E6 | K6: Supplier C | L6: 327.71 | M6: 3 | N6: 20 | O6: 93.897872
A7: SKU004 | B7: Bluetooth Speaker | C7: Electronics | D7: 180 | E7: 89 | F7: 3 | G7: 11 | H7: 9 | I7: =F7*G7+H7 | J7: =D7*E7 | K7: Supplier C | L7: 180.38 | M7: 4 | N7: 10 | O7: 86.301287
A8: SKU005 | B8: Power Bank | C8: Electronics | D8: 800 | E8: 333 | F8: 16 | G8: 6 | H8: 80 | I8: =F8*G8+H8 | J8: =D8*E8 | K8: Supplier A | L8: 802.66 | M8: 3 | N8: 10 | O8: 96.129774
A9: SKU006 | B9: Desk Lamp | C9: Home | D9: 220 | E9: 49 | F9: 3 | G9: 5 | H9: 15 | I9: =F9*G9+H9 | J9: =D9*E9 | K9: Supplier A | L9: 198.58 | M9: 11 | N9: 10 | O9: 84.015909
A10: SKU007 | B10: Storage Box | C10: Home | D10: 220 | E10: 40 | F10: 7 | G10: 6 | H10: 28 | I10: =F10*G10+H10 | J10: =D10*E10 | K10: Supplier B | L10: 259.3 | M10: 11 | N10: 50 | O10: 90.067612
A11: SKU008 | B11: Water Bottle | C11: Lifestyle | D11: 120 | E11: 206 | F11: 15 | G11: 4 | H11: 60 | I11: =F11*G11+H11 | J11: =D11*E11 | K11: Supplier A | L11: 126.63 | M11: 11 | N11: 20 | O11: 77.747539
A12: SKU009 | B12: Travel Mug | C12: Lifestyle | D12: 500 | E12: 85 | F12: 11 | G12: 3 | H12: 55 | I12: =F12*G12+H12 | J12: =D12*E12 | K12: Supplier C | L12: 485 | M12: 8 | N12: 10 | O12: 90.213093
A13: SKU010 | B13: Notebook Set | C13: Stationery | D13: 1500 | E13: 351 | F13: 15 | G13: 4 | H13: 60 | I13: =F13*G13+H13 | J13: =D13*E13 | K13: Supplier A | L13: 1573.35 | M13: 4 | N13: 10 | O13: 93.994459
A14: SKU011 | B14: Ballpoint Pens | C14: Stationery | D14: 500 | E14: 388 | F14: 14 | G14: 12 | H14: 42 | I14: =F14*G14+H14 | J14: =D14*E14 | K14: Supplier A | L14: 538.1 | M14: 3 | N14: 25 | O14: 88.275647
A15: SKU012 | B15: Backpack | C15: Lifestyle | D15: 120 | E15: 18 | F15: 4 | G15: 6 | H15: 16 | I15: =F15*G15+H15 | J15: =D15*E15 | K15: Supplier C | L15: 117.61 | M15: 5 | N15: 25 | O15: 95.337709
... A33: SKU030 | B33: Pen Holder | C33: Stationery | D33: 250 | E33: 169 | F33: 8 | G33: 11 | H33: 16 | I33: =F33*G33+H33 | J33: =D33*E33 | K33: Supplier B | L33: 225.7 | M33: 13 | N33: 20 | O33: 87.253395

Sheet Supplier_Comparison
A1: Supplier Comparison
A2: Compare price, lead time, MOQ, quality and reliability. Scores are relative within each SKU.
A3: SKU | B3: Product | C3: Supplier | D3: Unit Price (₹) | E3: Lead Time (days) | F3: MOQ (units) | G3: Defect Rate (%) | H3: On-time Delivery (%) | I3: Price Score (0-100) | J3: Lead Score (0-100) | K3: Quality Score (0-100) | L3: Reliability Score (0-100) | M3: Weighted Score | N3: Rank per SKU
A4: SKU001 | B4: Wireless Mouse | C4: Supplier A | D4: 635.21 | E4: 3 | F4: 10 | G4: 4.2 | H4: 97.9 | I4: =MIN($D$4:$D$6)/D4*100 | J4: =MIN($E$4:$E$6)/E4*100 | K4: =MIN($G$4:$G$6)/G4*100 | L4: =H4 | M4: =I4*40%+J4*25%+K4*20%+L4*15% | N4: =RANK(M4,$M$4:$M$6,0)
A5: SKU001 | B5: Wireless Mouse | C5: Supplier B | D5: 734.17 | E5: 7 | F5: 20 | G5: 0.54 | H5: 97.9 | I5: =MIN($D$4:$D$6)/D5*100 | J5: =MIN($E$4:$E$6)/E5*100 | K5: =MIN($G$4:$G$6)/G5*100 | L5: =H5 | M5: =I5*40%+J5*25%+K5*20%+L5*15% | N5: =RANK(M5,$M$4:$M$6,0)
A6: SKU001 | B6: Wireless Mouse | C6: Supplier C | D6: 756.66 | E6: 4 | F6: 50 | G6: 3.73 | H6: 99.2 | I6: =MIN($D$4:$D$6)/D6*100 | J6: =MIN($E$4:$E$6)/E6*100 | K6: =MIN($G$4:$G$6)/G6*100 | L6: =H6 | M6: =I6*40%+J6*25%+K6*20%+L6*15% | N6: =RANK(M6,$M$4:$M$6,0)
A7: SKU002 | B7: USB-C Cable | C7: Supplier A | D7: 187.17 | E7: 5 | F7: 20 | G7: 3.07 | H7: 98.8 | I7: =MIN($D$7:$D$9)/D7*100 | J7: =MIN($E$7:$E$9)/E7*100 | K7: =MIN($G$7:$G$9)/G7*100 | L7: =H7 | M7: =I7*40%+J7*25%+K7*20%+L7*15% | N7: =RANK(M7,$M$7:$M$9,0)
A8: SKU002 | B8: USB-C Cable | C8: Supplier B | D8: 167.32 | E8: 11 | F8: 50 | G8: 4.35 | H8: 98.5 | I8: =MIN($D$7:$D$9)/D8*100 | J8: =MIN($E$7:$E$9)/E8*100 | K8: =MIN($G$7:$G$9)/G8*100 | L8: =H8 | M8: =I8*40%+J8*25%+K8*20%+L8*15% | N8: =RANK(M8,$M$7:$M$9,0)
A9: SKU002 | B9: USB-C Cable | C9: Supplier C | D9: 199.18 | E9: 6 | F9: 25 | G9: 1.98 | H9: 95.1 | I9: =MIN($D$7:$D$9)/D9*100 | J9: =MIN($E$7:$E$9)/E9*100 | K9: =MIN($G$7:$G$9)/G9*100 | L9: =H9 | M9: =I9*40%+J9*25%+K9*20%+L9*15% | N9: =RANK(M9,$M$7:$M$9,0)
A10: SKU003 | B10: Laptop Stand | C10: Supplier A | D10: 297.61 | E10: 11 | F10: 50 | G10: 0.81 | H10: 89 | I10: =MIN($D$10:$D$12)/D10*100 | J10: =MIN($E$10:$E$12)/E10*100 | K10: =MIN($G$10:$G$12)/G10*100 | L10: =H10 | M10: =I10*40%+J10*25%+K10*20%+L10*15% | N10: =RANK(M10,$M$10:$M$12,0)
A11: SKU003 | B11: Laptop Stand | C11: Supplier B | D11: 294.43 | E11: 12 | F11: 20 | G11: 2.77 | H11: 86.1 | I11: =MIN($D$10:$D$12)/D11*100 | J11: =MIN($E$10:$E$12)/E11*100 | K11: =MIN($G$10:$G$12)/G11*100 | L11: =H11 | M11: =I11*40%+J11*25%+K11*20%+L11*15% | N11: =RANK(M11,$M$10:$M$12,0)
A12: SKU003 | B12: Laptop Stand | C12: Supplier C | D12: 327.71 | E12: 3 | F12: 20 | G12: 0.58 | H12: 86.4 | I12: =MIN($D$10:$D$12)/D12*100 | J12: =MIN($E$10:$E$12)/E12*100 | K12: =MIN($G$10:$G$12)/G12*100 | L12: =H12 | M12: =I12*40%+J12*25%+K12*20%+L12*15% | N12: =RANK(M12,$M$10:$M$12,0)
A13: SKU004 | B13: Bluetooth Speaker | C13: Supplier A | D13: 176.24 | E13: 11 | F13: 20 | G13: 1.47 | H13: 92.6 | I13: =MIN($D$13:$D$15)/D13*100 | J13: =MIN($E$13:$E$15)/E13*100 | K13: =MIN($G$13:$G$15)/G13*100 | L13: =H13 | M13: =I13*40%+J13*25%+K13*20%+L13*15% | N13: =RANK(M13,$M$13:$M$15,0)
A14: SKU004 | B14: Bluetooth Speaker | C14: Supplier B | D14: 187.52 | E14: 12 | F14: 50 | G14: 1.32 | H14: 92.4 | I14: =MIN($D$13:$D$15)/D14*100 | J14: =MIN($E$13:$E$15)/E14*100 | K14: =MIN($G$13:$G$15)/G14*100 | L14: =H14 | M14: =I14*40%+J14*25%+K14*20%+L14*15% | N14: =RANK(M14,$M$13:$M$15,0)
A15: SKU004 | B15: Bluetooth Speaker | C15: Supplier C | D15: 180.38 | E15: 4 | F15: 10 | G15: 3.07 | H15: 90.8 | I15: =MIN($D$13:$D$15)/D15*100 | J15: =MIN($E$13:$E$15)/E15*100 | K15: =MIN($G$13:$G$15)/G15*100 | L15: =H15 | M15: =I15*40%+J15*25%+K15*20%+L15*15% | N15: =RANK(M15,$M$13:$M$15,0)
A16: SKU005 | B16: Power Bank | C16: Supplier A | D16: 802.66 | E16: 3 | F16: 10 | G16: 0.55 | H16: 95.8 | I16: =MIN($D$16:$D$18)/D16*100 | J16: =MIN($E$16:$E$18)/E16*100 | K16: =MIN($G$16:$G$18)/G16*100 | L16: =H16 | M16: =I16*40%+J16*25%+K16*20%+L16*15% | N16: =RANK(M16,$M$16:$M$18,0)
A17: SKU005 | B17: Power Bank | C17: Supplier B | D17: 896.14 | E17: 4 | F17: 20 | G17: 1.1 | H17: 93.2 | I17: =MIN($D$16:$D$18)/D17*100 | J17: =MIN($E$16:$E$18)/E17*100 | K17: =MIN($G$16:$G$18)/G17*100 | L17: =H17 | M17: =I17*40%+J17*25%+K17*20%+L17*15% | N17: =RANK(M17,$M$16:$M$18,0)
A18: SKU005 | B18: Power Bank | C18: Supplier C | D18: 737.64 | E18: 5 | F18: 25 | G18: 2.24 | H18: 97.8 | I18: =MIN($D$16:$D$18)/D18*100 | J18: =MIN($E$16:$E$18)/E18*100 | K18: =MIN($G$16:$G$18)/G18*100 | L18: =H18 | M18: =I18*40%+J18*25%+K18*20%+L18*15% | N18: =RANK(M18,$M$16:$M$18,0)
A19: SKU006 | B19: Desk Lamp | C19: Supplier A | D19: 198.58 | E19: 11 | F19: 10 | G19: 0.51 | H19: 99.5 | I19: =MIN($D$19:$D$21)/D19*100 | J19: =MIN($E$19:$E$21)/E19*100 | K19: =MIN($G$19:$G$21)/G19*100 | L19: =H19 | M19: =I19*40%+J19*25%+K19*20%+L19*15% | N19: =RANK(M19,$M$19:$M$21,0)
A20: SKU006 | B20: Desk Lamp | C20: Supplier B | D20: 248.78 | E20: 4 | F20: 20 | G20: 1 | H20: 92.6 | I20: =MIN($D$19:$D$21)/D20*100 | J20: =MIN($E$19:$E$21)/E20*100 | K20: =MIN($G$19:$G$21)/G20*100 | L20: =H20 | M20: =I20*40%+J20*25%+K20*20%+L20*15% | N20: =RANK(M20,$M$19:$M$21,0)
A21: SKU006 | B21: Desk Lamp | C21: Supplier C | D21: 207.71 | E21: 9 | F21: 10 | G21: 0.99 | H21: 86 | I21: =MIN($D$19:$D$21)/D21*100 | J21: =MIN($E$19:$E$21)/E21*100 | K21: =MIN($G$19:$G$21)/G21*100 | L21: =H21 | M21: =I21*40%+J21*25%+K21*20%+L21*15% | N21: =RANK(M21,$M$19:$M$21,0)
A22: SKU007 | B22: Storage Box | C22: Supplier A | D22: 219.37 | E22: 10 | F22: 25 | G22: 2.08 | H22: 98.9 | I22: =MIN($D$22:$D$24)/D22*100 | J22: =MIN($E$22:$E$24)/E22*100 | K22: =MIN($G$22:$G$24)/G22*100 | L22: =H22 | M22: =I22*40%+J22*25%+K22*20%+L22*15% | N22: =RANK(M22,$M$22:$M$24,0)
A23: SKU007 | B23: Storage Box | C23: Supplier B | D23: 259.3 | E23: 11 | F23: 50 | G23: 0.95 | H23: 90 | I23: =MIN($D$22:$D$24)/D23*100 | J23: =MIN($E$22:$E$24)/E23*100 | K23: =MIN($G$22:$G$24)/G23*100 | L23: =H23 | M23: =I23*40%+J23*25%+K23*20%+L23*15% | N23: =RANK(M23,$M$22:$M$24,0)
A24: SKU007 | B24: Storage Box | C24: Supplier C | D24: 257.53 | E24: 12 | F24: 10 | G24: 3.44 | H24: 86.8 | I24: =MIN($D$22:$D$24)/D24*100 | J24: =MIN($E$22:$E$24)/E24*100 | K24: =MIN($G$22:$G$24)/G24*100 | L24: =H24 | M24: =I24*40%+J24*25%+K24*20%+L24*15% | N24: =RANK(M24,$M$22:$M$24,0)
A25: SKU008 | B25: Water Bottle | C25: Supplier A | D25: 126.63 | E25: 11 | F25: 20 | G25: 0.54 | H25: 92.9 | I25: =MIN($D$25:$D$27)/D25*100 | J25: =MIN($E$25:$E$27)/E25*100 | K25: =MIN($G$25:$G$27)/G25*100 | L25: =H25 | M25: =I25*40%+J25*25%+K25*20%+L25*15% | N25: =RANK(M25,$M$25:$M$27,0)
A26: SKU008 | B26: Water Bottle | C26: Supplier B | D26: 136.25 | E26: 4 | F26: 10 | G26: 3.14 | H26: 89.2 | I26: =MIN($D$25:$D$27)/D26*100 | J26: =MIN($E$25:$E$27)/E26*100 | K26: =MIN($G$25:$G$27)/G26*100 | L26: =H26 | M26: =I26*40%+J26*25%+K26*20%+L26*15% | N26: =RANK(M26,$M$25:$M$27,0)
A27: SKU008 | B27: Water Bottle | C27: Supplier C | D27: 109.92 | E27: 12 | F27: 20 | G27: 2.73 | H27: 86.5 | I27: =MIN($D$25:$D$27)/D27*100 | J27: =MIN($E$25:$E$27)/E27*100 | K27: =MIN($G$25:$G$27)/G27*100 | L27: =H27 | M27: =I27*40%+J27*25%+K27*20%+L27*15% | N27: =RANK(M27,$M$25:$M$27,0)
A28: SKU009 | B28: Travel Mug | C28: Supplier A | D28: 452.3 | E28: 13 | F28: 25 | G28: 4.23 | H28: 88.8 | I28: =MIN($D$28:$D$30)/D28*100 | J28: =MIN($E$28:$E$30)/E28*100 | K28: =MIN($G$28:$G$30)/G28*100 | L28: =H28 | M28: =I28*40%+J28*25%+K28*20%+L28*15% | N28: =RANK(M28,$M$28:$M$30,0)
A29: SKU009 | B29: Travel Mug | C29: Supplier B | D29: 547.43 | E29: 6 | F29: 25 | G29: 1.96 | H29: 95.1 | I29: =MIN($D$28:$D$30)/D29*100 | J29: =MIN($E$28:$E$30)/E29*100 | K29: =MIN($G$28:$G$30)/G29*100 | L29: =H29 | M29: =I29*40%+J29*25%+K29*20%+L29*15% | N29: =RANK(M29,$M$28:$M$30,0)
A30: SKU009 | B30: Travel Mug | C30: Supplier C | D30: 485 | E30: 8 | F30: 10 | G30: 0.34 | H30: 94.4 | I30: =MIN($D$28:$D$30)/D30*100 | J30: =MIN($E$28:$E$30)/E30*100 | K30: =MIN($G$28:$G$30)/G30*100 | L30: =H30 | M30: =I30*40%+J30*25%+K30*20%+L30*15% | N30: =RANK(M30,$M$28:$M$30,0)
A31: SKU010 | B31: Notebook Set | C31: Supplier A | D31: 1573.35 | E31: 4 | F31: 10 | G31: 2.56 | H31: 92.8 | I31: =MIN($D$31:$D$33)/D31*100 | J31: =MIN($E$31:$E$33)/E31*100 | K31: =MIN($G$31:$G$33)/G31*100 | L31: =H31 | M31: =I31*40%+J31*25%+K31*20%+L31*15% | N31: =RANK(M31,$M$31:$M$33,0)
A32: SKU010 | B32: Notebook Set | C32: Supplier B | D32: 1379.61 | E32: 8 | F32: 10 | G32: 3.99 | H32: 91 | I32: =MIN($D$31:$D$33)/D32*100 | J32: =MIN($E$31:$E$33)/E32*100 | K32: =MIN($G$31:$G$33)/G32*100 | L32: =H32 | M32: =I32*40%+J32*25%+K32*20%+L32*15% | N32: =RANK(M32,$M$31:$M$33,0)
A33: SKU010 | B33: Notebook Set | C33: Supplier C | D33: 1390.99 | E33: 11 | F33: 25 | G33: 2.87 | H33: 99.3 | I33: =MIN($D$31:$D$33)/D33*100 | J33: =MIN($E$31:$E$33)/E33*100 | K33: =MIN($G$31:$G$33)/G33*100 | L33: =H33 | M33: =I33*40%+J33*25%+K33*20%+L33*15% | N33: =RANK(M33,$M$31:$M$33,0)
A34: SKU011 | B34: Ballpoint Pens | C34: Supplier A | D34: 538.1 | E34: 3 | F34: 25 | G34: 4.21 | H34: 87.4 | I34: =MIN($D$34:$D$36)/D34*100 | J34: =MIN($E$34:$E$36)/E34*100 | K34: =MIN($G$34:$G$36)/G34*100 | L34: =H34 | M34: =I34*40%+J34*25%+K34*20%+L34*15% | N34: =RANK(M34,$M$34:$M$36,0)
A35: SKU011 | B35: Ballpoint Pens | C35: Supplier B | D35: 571.72 | E35: 7 | F35: 10 | G35: 4.04 | H35: 96 | I35: =MIN($D$34:$D$36)/D35*100 | J35: =MIN($E$34:$E$36)/E35*100 | K35: =MIN($G$34:$G$36)/G35*100 | L35: =H35 | M35: =I35*40%+J35*25%+K35*20%+L35*15% | N35: =RANK(M35,$M$34:$M$36,0)
A36: SKU011 | B36: Ballpoint Pens | C36: Supplier C | D36: 463.32 | E36: 7 | F36: 20 | G36: 3.31 | H36: 88.7 | I36: =MIN($D$34:$D$36)/D36*100 | J36: =MIN($E$34:$E$36)/E36*100 | K36: =MIN($G$34:$G$36)/G36*100 | L36: =H36 | M36: =I36*40%+J36*25%+K36*20%+L36*15% | N36: =RANK(M36,$M$34:$M$36,0)
A37: SKU012 | B37: Backpack | C37: Supplier A | D37: 128.43 | E37: 7 | F37: 50 | G37: 1.35 | H37: 98.3 | I37: =MIN($D$37:$D$39)/D37*100 | J37: =MIN($E$37:$E$39)/E37*100 | K37: =MIN($G$37:$G$39)/G37*100 | L37: =H37 | M37: =I37*40%+J37*25%+K37*20%+L37*15% | N37: =RANK(M37,$M$37:$M$39,0)
A38: SKU012 | B38: Backpack | C38: Supplier B | D38: 107.43 | E38: 13 | F38: 50 | G38: 3.78 | H38: 86.6 | I38: =MIN($D$37:$D$39)/D38*100 | J38: =MIN($E$37:$E$39)/E38*100 | K38: =MIN($G$37:$G$39)/G38*100 | L38: =H38 | M38: =I38*40%+J38*25%+K38*20%+L38*15% | N38: =RANK(M38,$M$37:$M$39,0)
A39: SKU012 | B39: Backpack | C39: Supplier C | D39: 117.61 | E39: 5 | F39: 25 | G39: 0.98 | H39: 92 | I39: =MIN($D$37:$D$39)/D39*100 | J39: =MIN($E$37:$E$39)/E39*100 | K39: =MIN($G$37:$G$39)/G39*100 | L39: =H39 | M39: =I39*40%+J39*25%+K39*20%+L39*15% | N39: =RANK(M39,$M$37:$M$39,0)
A40: SKU013 | B40: Phone Case | C40: Supplier A | D40: 1310.04 | E40: 11 | F40: 10 | G40: 0.77 | H40: 98.8 | I40: =MIN($D$40:$D$42)/D40*100 | J40: =MIN($E$40:$E$42)/E40*100 | K40: =MIN($G$40:$G$42)/G40*100 | L40: =H40 | M40: =I40*40%+J40*25%+K40*20%+L40*15% | N40: =RANK(M40,$M$40:$M$42,0)
A41: SKU013 | B41: Phone Case | C41: Supplier B | D41: 1304.77 | E41: 5 | F41: 10 | G41: 3.81 | H41: 93.9 | I41: =MIN($D$40:$D$42)/D41*100 | J41: =MIN($E$40:$E$42)/E41*100 | K41: =MIN($G$40:$G$42)/G41*100 | L41: =H41 | M41: =I41*40%+J41*25%+K41*20%+L41*15% | N41: =RANK(M41,$M$40:$M$42,0)
A42: SKU013 | B42: Phone Case | C42: Supplier C | D42: 1109.31 | E42: 5 | F42: 10 | G42: 1.59 | H42: 98.1 | I42: =MIN($D$40:$D$42)/D42*100 | J42: =MIN($E$40:$E$42)/E42*100 | K42: =MIN($G$40:$G$42)/G42*100 | L42: =H42 | M42: =I42*40%+J42*25%+K42*20%+L42*15% | N42: =RANK(M42,$M$40:$M$42,0)
A43: SKU014 | B43: Keyboard | C43: Supplier A | D43: 391.59 | E43: 3 | F43: 25 | G43: 1.18 | H43: 89.4 | I43: =MIN($D$43:$D$45)/D43*100 | J43: =MIN($E$43:$E$45)/E43*100 | K43: =MIN($G$43:$G$45)/G43*100 | L43: =H43 | M43: =I43*40%+J43*25%+K43*20%+L43*15% | N43: =RANK(M43,$M$43:$M$45,0)
A44: SKU014 | B44: Keyboard | C44: Supplier B | D44: 318.79 | E44: 11 | F44: 50 | G44: 4.39 | H44: 96.1 | I44: =MIN($D$43:$D$45)/D44*100 | J44: =MIN($E$43:$E$45)/E44*100 | K44: =MIN($G$43:$G$45)/G44*100 | L44: =H44 | M44: =I44*40%+J44*25%+K44*20%+L44*15% | N44: =RANK(M44,$M$43:$M$45,0)
A45: SKU014 | B45: Keyboard | C45: Supplier C | D45: 405.21 | E45: 6 | F45: 20 | G45: 4.4 | H45: 96.9 | I45: =MIN($D$43:$D$45)/D45*100 | J45: =MIN($E$43:$E$45)/E45*100 | K45: =MIN($G$43:$G$45)/G45*100 | L45: =H45 | M45: =I45*40%+J45*25%+K45*20%+L45*15% | N45: =RANK(M45,$M$43:$M$45,0)
A46: SKU015 | B46: Monitor Riser | C46: Supplier A | D46: 206 | E46: 3 | F46: 20 | G46: 3.39 | H46: 90.5 | I46: =MIN($D$46:$D$48)/D46*100 | J46: =MIN($E$46:$E$48)/E46*100 | K46: =MIN($G$46:$G$48)/G46*100 | L46: =H46 | M46: =I46*40%+J46*25%+K46*20%+L46*15% | N46: =RANK(M46,$M$46:$M$48,0)
A47: SKU015 | B47: Monitor Riser | C47: Supplier B | D47: 208.66 | E47: 13 | F47: 20 | G47: 1.42 | H47: 96.6 | I47: =MIN($D$46:$D$48)/D47*100 | J47: =MIN($E$46:$E$48)/E47*100 | K47: =MIN($G$46:$G$48)/G47*100 | L47: =H47 | M47: =I47*40%+J47*25%+K47*20%+L47*15% | N47: =RANK(M47,$M$46:$M$48,0)
A48: SKU015 | B48: Monitor Riser | C48: Supplier C | D48: 164.24 | E48: 3 | F48: 50 | G48: 1.23 | H48: 97 | I48: =MIN($D$46:$D$48)/D48*100 | J48: =MIN($E$46:$E$48)/E48*100 | K48: =MIN($G$46:$G$48)/G48*100 | L48: =H48 | M48: =I48*40%+J48*25%+K48*20%+L48*15% | N48: =RANK(M48,$M$46:$M$48,0)
A49: SKU016 | B49: Yoga Mat | C49: Supplier A | D49: 814.47 | E49: 7 | F49: 20 | G49: 1.24 | H49: 94.9 | I49: =MIN($D$49:$D$51)/D49*100 | J49: =MIN($E$49:$E$51)/E49*100 | K49: =MIN($G$49:$G$51)/G49*100 | L49: =H49 | M49: =I49*40%+J49*25%+K49*20%+L49*15% | N49: =RANK(M49,$M$49:$M$51,0)
A50: SKU016 | B50: Yoga Mat | C50: Supplier B | D50: 799.63 | E50: 7 | F50: 10 | G50: 4.36 | H50: 89.8 | I50: =MIN($D$49:$D$51)/D50*100 | J50: =MIN($E$49:$E$51)/E50*100 | K50: =MIN($G$49:$G$51)/G50*100 | L50: =H50 | M50: =I50*40%+J50*25%+K50*20%+L50*15% | N50: =RANK(M50,$M$49:$M$51,0)
A51: SKU016 | B51: Yoga Mat | C51: Supplier C | D51: 857.96 | E51: 9 | F51: 25 | G51: 4.24 | H51: 87.6 | I51: =MIN($D$49:$D$51)/D51*100 | J51: =MIN($E$49:$E$51)/E51*100 | K51: =MIN($G$49:$G$51)/G51*100 | L51: =H51 | M51: =I51*40%+J51*25%+K51*20%+L51*15% | N51: =RANK(M51,$M$49:$M$51,0)
A52: SKU017 | B52: Resistance Bands | C52: Supplier A | D52: 257.65 | E52: 5 | F52: 25 | G52: 0.46 | H52: 94.1 | I52: =MIN($D$52:$D$54)/D52*100 | J52: =MIN($E$52:$E$54)/E52*100 | K52: =MIN($G$52:$G$54)/G52*100 | L52: =H52 | M52: =I52*40%+J52*25%+K52*20%+L52*15% | N52: =RANK(M52,$M$52:$M$54,0)
A53: SKU017 | B53: Resistance Bands | C53: Supplier B | D53: 216.42 | E53: 8 | F53: 50 | G53: 2.85 | H53: 92.9 | I53: =MIN($D$52:$D$54)/D53*100 | J53: =MIN($E$52:$E$54)/E53*100 | K53: =MIN($G$52:$G$54)/G53*100 | L53: =H53 | M53: =I53*40%+J53*25%+K53*20%+L53*15% | N53: =RANK(M53,$M$52:$M$54,0)
A54: SKU017 | B54: Resistance Bands | C54: Supplier C | D54: 219.02 | E54: 12 | F54: 20 | G54: 1.37 | H54: 95.6 | I54: =MIN($D$52:$D$54)/D54*100 | J54: =MIN($E$52:$E$54)/E54*100 | K54: =MIN($G$52:$G$54)/G54*100 | L54: =H54 | M54: =I54*40%+J54*25%+K54*20%+L54*15% | N54: =RANK(M54,$M$52:$M$54,0)
A55: SKU018 | B55: Running Bottle | C55: Supplier A | D55: 1056.61 | E55: 11 | F55: 20 | G55: 1.83 | H55: 86.9 | I55: =MIN($D$55:$D$57)/D55*100 | J55: =MIN($E$55:$E$57)/E55*100 | K55: =MIN($G$55:$G$57)/G55*100 | L55: =H55 | M55: =I55*40%+J55*25%+K55*20%+L55*15% | N55: =RANK(M55,$M$55:$M$57,0)
A56: SKU018 | B56: Running Bottle | C56: Supplier B | D56: 1295.13 | E56: 8 | F56: 25 | G56: 3.09 | H56: 87.7 | I56: =MIN($D$55:$D$57)/D56*100 | J56: =MIN($E$55:$E$57)/E56*100 | K56: =MIN($G$55:$G$57)/G56*100 | L56: =H56 | M56: =I56*40%+J56*25%+K56*20%+L56*15% | N56: =RANK(M56,$M$55:$M$57,0)
A57: SKU018 | B57: Running Bottle | C57: Supplier C | D57: 1380.02 | E57: 11 | F57: 25 | G57: 3.1 | H57: 90.4 | I57: =MIN($D$55:$D$57)/D57*100 | J57: =MIN($E$55:$E$57)/E57*100 | K57: =MIN($G$55:$G$57)/G57*100 | L57: =H57 | M57: =I57*40%+J57*25%+K57*20%+L57*15% | N57: =RANK(M57,$M$55:$M$57,0)
A58: SKU019 | B58: Lunch Container | C58: Supplier A | D58: 130.7 | E58: 11 | F58: 20 | G58: 1.11 | H58: 95 | I58: =MIN($D$58:$D$60)/D58*100 | J58: =MIN($E$58:$E$60)/E58*100 | K58: =MIN($G$58:$G$60)/G58*100 | L58: =H58 | M58: =I58*40%+J58*25%+K58*20%+L58*15% | N58: =RANK(M58,$M$58:$M$60,0)
A59: SKU019 | B59: Lunch Container | C59: Supplier B | D59: 119.25 | E59: 5 | F59: 25 | G59: 2.01 | H59: 97.3 | I59: =MIN($D$58:$D$60)/D59*100 | J59: =MIN($E$58:$E$60)/E59*100 | K59: =MIN($G$58:$G$60)/G59*100 | L59: =H59 | M59: =I59*40%+J59*25%+K59*20%+L59*15% | N59: =RANK(M59,$M$58:$M$60,0)
A60: SKU019 | B60: Lunch Container | C60: Supplier C | D60: 116.54 | E60: 6 | F60: 50 | G60: 3.6 | H60: 94.2 | I60: =MIN($D$58:$D$60)/D60*100 | J60: =MIN($E$58:$E$60)/E60*100 | K60: =MIN($G$58:$G$60)/G60*100 | L60: =H60 | M60: =I60*40%+J60*25%+K60*20%+L60*15% | N60: =RANK(M60,$M$58:$M$60,0)
A61: SKU020 | B61: Bedside Organizer | C61: Supplier A | D61: 634.84 | E61: 10 | F61: 50 | G61: 3.14 | H61: 92.9 | I61: =MIN($D$61:$D$63)/D61*100 | J61: =MIN($E$61:$E$63)/E61*100 | K61: =MIN($G$61:$G$63)/G61*100 | L61: =H61 | M61: =I61*40%+J61*25%+K61*20%+L61*15% | N61: =RANK(M61,$M$61:$M$63,0)
A62: SKU020 | B62: Bedside Organizer | C62: Supplier B | D62: 726.78 | E62: 5 | F62: 10 | G62: 1.49 | H62: 95 | I62: =MIN($D$61:$D$63)/D62*100 | J62: =MIN($E$61:$E$63)/E62*100 | K62: =MIN($G$61:$G$63)/G62*100 | L62: =H62 | M62: =I62*40%+J62*25%+K62*20%+L62*15% | N62: =RANK(M62,$M$61:$M$63,0)
A63: SKU020 | B63: Bedside Organizer | C63: Supplier C | D63: 692.76 | E63: 4 | F63: 20 | G63: 3.13 | H63: 89 | I63: =MIN($D$61:$D$63)/D63*100 | J63: =MIN($E$61:$E$63)/E63*100 | K63: =MIN($G$61:$G$63)/G63*100 | L63: =H63 | M63: =I63*40%+J63*25%+K63*20%+L63*15% | N63: =RANK(M63,$M$61:$M$63,0)
A64: SKU021 | B64: Charging Adapter | C64: Supplier A | D64: 206.74 | E64: 3 | F64: 10 | G64: 1.33 | H64: 92.4 | I64: =MIN($D$64:$D$66)/D64*100 | J64: =MIN($E$64:$E$66)/E64*100 | K64: =MIN($G$64:$G$66)/G64*100 | L64: =H64 | M64: =I64*40%+J64*25%+K64*20%+L64*15% | N64: =RANK(M64,$M$64:$M$66,0)
A65: SKU021 | B65: Charging Adapter | C65: Supplier B | D65: 249.68 | E65: 4 | F65: 50 | G65: 2.04 | H65: 94.5 | I65: =MIN($D$64:$D$66)/D65*100 | J65: =MIN($E$64:$E$66)/E65*100 | K65: =MIN($G$64:$G$66)/G65*100 | L65: =H65 | M65: =I65*40%+J65*25%+K65*20%+L65*15% | N65: =RANK(M65,$M$64:$M$66,0)
A66: SKU021 | B66: Charging Adapter | C66: Supplier C | D66: 206.43 | E66: 9 | F66: 50 | G66: 1.98 | H66: 88 | I66: =MIN($D$64:$D$66)/D66*100 | J66: =MIN($E$64:$E$66)/E66*100 | K66: =MIN($G$64:$G$66)/G66*100 | L66: =H66 | M66: =I66*40%+J66*25%+K66*20%+L66*15% | N66: =RANK(M66,$M$64:$M$66,0)
A67: SKU022 | B67: Headphones | C67: Supplier A | D67: 325.89 | E67: 4 | F67: 50 | G67: 1.22 | H67: 96.9 | I67: =MIN($D$67:$D$69)/D67*100 | J67: =MIN($E$67:$E$69)/E67*100 | K67: =MIN($G$67:$G$69)/G67*100 | L67: =H67 | M67: =I67*40%+J67*25%+K67*20%+L67*15% | N67: =RANK(M67,$M$67:$M$69,0)
A68: SKU022 | B68: Headphones | C68: Supplier B | D68: 326.63 | E68: 10 | F68: 10 | G68: 2.64 | H68: 98.4 | I68: =MIN($D$67:$D$69)/D68*100 | J68: =MIN($E$67:$E$69)/E68*100 | K68: =MIN($G$67:$G$69)/G68*100 | L68: =H68 | M68: =I68*40%+J68*25%+K68*20%+L68*15% | N68: =RANK(M68,$M$67:$M$69,0)
A69: SKU022 | B69: Headphones | C69: Supplier C | D69: 274.92 | E69: 5 | F69: 50 | G69: 3.1 | H69: 99.3 | I69: =MIN($D$67:$D$69)/D69*100 | J69: =MIN($E$67:$E$69)/E69*100 | K69: =MIN($G$67:$G$69)/G69*100 | L69: =H69 | M69: =I69*40%+J69*25%+K69*20%+L69*15% | N69: =RANK(M69,$M$67:$M$69,0)
A70: SKU023 | B70: Packing Cubes | C70: Supplier A | D70: 444.63 | E70: 10 | F70: 50 | G70: 3.79 | H70: 93.4 | I70: =MIN($D$70:$D$72)/D70*100 | J70: =MIN($E$70:$E$72)/E70*100 | K70: =MIN($G$70:$G$72)/G70*100 | L70: =H70 | M70: =I70*40%+J70*25%+K70*20%+L70*15% | N70: =RANK(M70,$M$70:$M$72,0)
A71: SKU023 | B71: Packing Cubes | C71: Supplier B | D71: 482.65 | E71: 10 | F71: 50 | G71: 1.39 | H71: 89.3 | I71: =MIN($D$70:$D$72)/D71*100 | J71: =MIN($E$70:$E$72)/E71*100 | K71: =MIN($G$70:$G$72)/G71*100 | L71: =H71 | M71: =I71*40%+J71*25%+K71*20%+L71*15% | N71: =RANK(M71,$M$70:$M$72,0)
A72: SKU023 | B72: Packing Cubes | C72: Supplier C | D72: 449.95 | E72: 11 | F72: 50 | G72: 2.93 | H72: 89.7 | I72: =MIN($D$70:$D$72)/D72*100 | J72: =MIN($E$70:$E$72)/E72*100 | K72: =MIN($G$70:$G$72)/G72*100 | L72: =H72 | M72: =I72*40%+J72*25%+K72*20%+L72*15% | N72: =RANK(M72,$M$70:$M$72,0)
A73: SKU024 | B73: Sticky Notes | C73: Supplier A | D73: 135.49 | E73: 7 | F73: 20 | G73: 1.44 | H73: 90.3 | I73: =MIN($D$73:$D$75)/D73*100 | J73: =MIN($E$73:$E$75)/E73*100 | K73: =MIN($G$73:$G$75)/G73*100 | L73: =H73 | M73: =I73*40%+J73*25%+K73*20%+L73*15% | N73: =RANK(M73,$M$73:$M$75,0)
A74: SKU024 | B74: Sticky Notes | C74: Supplier B | D74: 156.31 | E74: 5 | F74: 20 | G74: 1.27 | H74: 95.4 | I74: =MIN($D$73:$D$75)/D74*100 | J74: =MIN($E$73:$E$75)/E74*100 | K74: =MIN($G$73:$G$75)/G74*100 | L74: =H74 | M74: =I74*40%+J74*25%+K74*20%+L74*15% | N74: =RANK(M74,$M$73:$M$75,0)
A75: SKU024 | B75: Sticky Notes | C75: Supplier C | D75: 163.79 | E75: 4 | F75: 50 | G75: 2.01 | H75: 93.3 | I75: =MIN($D$73:$D$75)/D75*100 | J75: =MIN($E$73:$E$75)/E75*100 | K75: =MIN($G$73:$G$75)/G75*100 | L75: =H75 | M75: =I75*40%+J75*25%+K75*20%+L75*15% | N75: =RANK(M75,$M$73:$M$75,0)
A76: SKU025 | B76: Desk Organizer | C76: Supplier A | D76: 301.42 | E76: 6 | F76: 50 | G76: 1.94 | H76: 96.4 | I76: =MIN($D$76:$D$78)/D76*100 | J76: =MIN($E$76:$E$78)/E76*100 | K76: =MIN($G$76:$G$78)/G76*100 | L76: =H76 | M76: =I76*40%+J76*25%+K76*20%+L76*15% | N76: =RANK(M76,$M$76:$M$78,0)
A77: SKU025 | B77: Desk Organizer | C77: Supplier B | D77: 349.15 | E77: 3 | F77: 50 | G77: 2.3 | H77: 98.7 | I77: =MIN($D$76:$D$78)/D77*100 | J77: =MIN($E$76:$E$78)/E77*100 | K77: =MIN($G$76:$G$78)/G77*100 | L77: =H77 | M77: =I77*40%+J77*25%+K77*20%+L77*15% | N77: =RANK(M77,$M$76:$M$78,0)
A78: SKU025 | B78: Desk Organizer | C78: Supplier C | D78: 290.88 | E78: 9 | F78: 50 | G78: 2.56 | H78: 95.9 | I78: =MIN($D$76:$D$78)/D78*100 | J78: =MIN($E$76:$E$78)/E78*100 | K78: =MIN($G$76:$G$78)/G78*100 | L78: =H78 | M78: =I78*40%+J78*25%+K78*20%+L78*15% | N78: =RANK(M78,$M$76:$M$78,0)
A79: SKU026 | B79: Fitness Towel | C79: Supplier A | D79: 727.97 | E79: 6 | F79: 50 | G79: 1.22 | H79: 91.9 | I79: =MIN($D$79:$D$81)/D79*100 | J79: =MIN($E$79:$E$81)/E79*100 | K79: =MIN($G$79:$G$81)/G79*100 | L79: =H79 | M79: =I79*40%+J79*25%+K79*20%+L79*15% | N79: =RANK(M79,$M$79:$M$81,0)
A80: SKU026 | B80: Fitness Towel | C80: Supplier B | D80: 577.66 | E80: 8 | F80: 50 | G80: 3.34 | H80: 97.3 | I80: =MIN($D$79:$D$81)/D80*100 | J80: =MIN($E$79:$E$81)/E80*100 | K80: =MIN($G$79:$G$81)/G80*100 | L80: =H80 | M80: =I80*40%+J80*25%+K80*20%+L80*15% | N80: =RANK(M80,$M$79:$M$81,0)
A81: SKU026 | B81: Fitness Towel | C81: Supplier C | D81: 751.31 | E81: 12 | F81: 10 | G81: 4.11 | H81: 94 | I81: =MIN($D$79:$D$81)/D81*100 | J81: =MIN($E$79:$E$81)/E81*100 | K81: =MIN($G$79:$G$81)/G81*100 | L81: =H81 | M81: =I81*40%+J81*25%+K81*20%+L81*15% | N81: =RANK(M81,$M$79:$M$81,0)
A82: SKU027 | B82: Reusable Bag | C82: Supplier A | D82: 269.72 | E82: 4 | F82: 50 | G82: 0.87 | H82: 92.2 | I82: =MIN($D$82:$D$84)/D82*100 | J82: =MIN($E$82:$E$84)/E82*100 | K82: =MIN($G$82:$G$84)/G82*100 | L82: =H82 | M82: =I82*40%+J82*25%+K82*20%+L82*15% | N82: =RANK(M82,$M$82:$M$84,0)
A83: SKU027 | B83: Reusable Bag | C83: Supplier B | D83: 223.77 | E83: 9 | F83: 25 | G83: 1.19 | H83: 90.4 | I83: =MIN($D$82:$D$84)/D83*100 | J83: =MIN($E$82:$E$84)/E83*100 | K83: =MIN($G$82:$G$84)/G83*100 | L83: =H83 | M83: =I83*40%+J83*25%+K83*20%+L83*15% | N83: =RANK(M83,$M$82:$M$84,0)
A84: SKU027 | B84: Reusable Bag | C84: Supplier C | D84: 277.09 | E84: 9 | F84: 25 | G84: 3.46 | H84: 97.2 | I84: =MIN($D$82:$D$84)/D84*100 | J84: =MIN($E$82:$E$84)/E84*100 | K84: =MIN($G$82:$G$84)/G84*100 | L84: =H84 | M84: =I84*40%+J84*25%+K84*20%+L84*15% | N84: =RANK(M84,$M$82:$M$84,0)
A85: SKU028 | B85: Drawer Dividers | C85: Supplier A | D85: 334.49 | E85: 4 | F85: 50 | G85: 0.38 | H85: 93.3 | I85: =MIN($D$85:$D$87)/D85*100 | J85: =MIN($E$85:$E$87)/E85*100 | K85: =MIN($G$85:$G$87)/G85*100 | L85: =H85 | M85: =I85*40%+J85*25%+K85*20%+L85*15% | N85: =RANK(M85,$M$85:$M$87,0)
A86: SKU028 | B86: Drawer Dividers | C86: Supplier B | D86: 412.99 | E86: 8 | F86: 20 | G86: 3.03 | H86: 96.5 | I86: =MIN($D$85:$D$87)/D86*100 | J86: =MIN($E$85:$E$87)/E86*100 | K86: =MIN($G$85:$G$87)/G86*100 | L86: =H86 | M86: =I86*40%+J86*25%+K86*20%+L86*15% | N86: =RANK(M86,$M$85:$M$87,0)
A87: SKU028 | B87: Drawer Dividers | C87: Supplier C | D87: 376.43 | E87: 3 | F87: 20 | G87: 1.14 | H87: 86.3 | I87: =MIN($D$85:$D$87)/D87*100 | J87: =MIN($E$85:$E$87)/E87*100 | K87: =MIN($G$85:$G$87)/G87*100 | L87: =H87 | M87: =I87*40%+J87*25%+K87*20%+L87*15% | N87: =RANK(M87,$M$85:$M$87,0)
A88: SKU029 | B88: Webcam Cover | C88: Supplier A | D88: 1388.57 | E88: 5 | F88: 50 | G88: 3.11 | H88: 93.6 | I88: =MIN($D$88:$D$90)/D88*100 | J88: =MIN($E$88:$E$90)/E88*100 | K88: =MIN($G$88:$G$90)/G88*100 | L88: =H88 | M88: =I88*40%+J88*25%+K88*20%+L88*15% | N88: =RANK(M88,$M$88:$M$90,0)
A89: SKU029 | B89: Webcam Cover | C89: Supplier B | D89: 1418.08 | E89: 7 | F89: 25 | G89: 1 | H89: 94.2 | I89: =MIN($D$88:$D$90)/D89*100 | J89: =MIN($E$88:$E$90)/E89*100 | K89: =MIN($G$88:$G$90)/G89*100 | L89: =H89 | M89: =I89*40%+J89*25%+K89*20%+L89*15% | N89: =RANK(M89,$M$88:$M$90,0)
A90: SKU029 | B90: Webcam Cover | C90: Supplier C | D90: 1656.57 | E90: 4 | F90: 20 | G90: 4.35 | H90: 87.5 | I90: =MIN($D$88:$D$90)/D90*100 | J90: =MIN($E$88:$E$90)/E90*100 | K90: =MIN($G$88:$G$90)/G90*100 | L90: =H90 | M90: =I90*40%+J90*25%+K90*20%+L90*15% | N90: =RANK(M90,$M$88:$M$90,0)
A91: SKU030 | B91: Pen Holder | C91: Supplier A | D91: 221.93 | E91: 7 | F91: 50 | G91: 1.97 | H91: 95.7 | I91: =MIN($D$91:$D$93)/D91*100 | J91: =MIN($E$91:$E$93)/E91*100 | K91: =MIN($G$91:$G$93)/G91*100 | L91: =H91 | M91: =I91*40%+J91*25%+K91*20%+L91*15% | N91: =RANK(M91,$M$91:$M$93,0)
A92: SKU030 | B92: Pen Holder | C92: Supplier B | D92: 225.7 | E92: 13 | F92: 20 | G92: 0.73 | H92: 96.4 | I92: =MIN($D$91:$D$93)/D92*100 | J92: =MIN($E$91:$E$93)/E92*100 | K92: =MIN($G$91:$G$93)/G92*100 | L92: =H92 | M92: =I92*40%+J92*25%+K92*20%+L92*15% | N92: =RANK(M92,$M$91:$M$93,0)
A93: SKU030 | B93: Pen Holder | C93: Supplier C | D93: 283.77 | E93: 12 | F93: 10 | G93: 3.64 | H93: 93.6 | I93: =MIN($D$91:$D$93)/D93*100 | J93: =MIN($E$91:$E$93)/E93*100 | K93: =MIN($G$91:$G$93)/G93*100 | L93: =H93 | M93: =I93*40%+J93*25%+K93*20%+L93*15% | N93: =RANK(M93,$M$91:$M$93,0)

Sheet Cost_Assumptions
A1: Cost & Scenario Assumptions
A2: Edit yellow cells to test different business conditions; values are illustrative, not industry benchmarks.
A3: Assumption | B3: Value | C3: Unit / explanation
A4: Annual holding cost rate | B4: 0.22 | C4: 22% of average inventory value per year
A5: Ordering cost per purchase order | B5: 450 | C5: ₹ per order
A6: Stockout penalty per unit | B6: 180 | C6: ₹ per unmet unit; used only as a risk proxy
A7: High-demand multiplier | B7: 1.3 | C7: 1.30 means demand increases by 30%
A8: Extra supplier delay | B8: 4 | C8: Additional days
A9: Extra target stock cover | B9: 14 | C9: Days of demand beyond lead-time and safety stock
A10: Planning horizon | B10: 30 | C10: Days used for illustrative scenario exposure

Sheet Replenishment_Plan
A1: Replenishment Plan
A2: Recommended quantities are model outputs. Check supplier MOQ and operational context before making a real order.
A3: SKU | B3: Product | C3: Current Stock | D3: Daily Demand | E3: Lead Time | F3: Safety Stock | G3: Reorder Point | H3: Status | I3: Target Stock | J3: Base Order Qty | K3: Supplier MOQ | L3: MOQ-Adjusted Order Qty | M3: Recommended Supplier | N3: Unit Price (₹) | O3: Purchase Cost (₹) | P3: Order Count | Q3: Annual Holding Cost (₹)
A4: =Inventory_Master!A4 | B4: =Inventory_Master!B4 | C4: =Inventory_Master!E4 | D4: =Inventory_Master!F4 | E4: =Inventory_Master!G4 | F4: =Inventory_Master!H4 | G4: =Inventory_Master!I4 | H4: =IF(C4<=G4,"REORDER","OK") | I4: =D4*E4+F4+D4*Cost_Assumptions!$B$9 | J4: =MAX(0,I4-C4) | K4: =Inventory_Master!N4 | L4: =IF(J4=0,0,MAX(J4,K4)) | M4: =Inventory_Master!K4 | N4: =Inventory_Master!L4 | O4: =L4*N4 | P4: =IF(L4>0,1,0) | Q4: =C4*Inventory_Master!D4*Cost_Assumptions!$B$4
A5: =Inventory_Master!A5 | B5: =Inventory_Master!B5 | C5: =Inventory_Master!E5 | D5: =Inventory_Master!F5 | E5: =Inventory_Master!G5 | F5: =Inventory_Master!H5 | G5: =Inventory_Master!I5 | H5: =IF(C5<=G5,"REORDER","OK") | I5: =D5*E5+F5+D5*Cost_Assumptions!$B$9 | J5: =MAX(0,I5-C5) | K5: =Inventory_Master!N5 | L5: =IF(J5=0,0,MAX(J5,K5)) | M5: =Inventory_Master!K5 | N5: =Inventory_Master!L5 | O5: =L5*N5 | P5: =IF(L5>0,1,0) | Q5: =C5*Inventory_Master!D5*Cost_Assumptions!$B$4
A6: =Inventory_Master!A6 | B6: =Inventory_Master!B6 | C6: =Inventory_Master!E6 | D6: =Inventory_Master!F6 | E6: =Inventory_Master!G6 | F6: =Inventory_Master!H6 | G6: =Inventory_Master!I6 | H6: =IF(C6<=G6,"REORDER","OK") | I6: =D6*E6+F6+D6*Cost_Assumptions!$B$9 | J6: =MAX(0,I6-C6) | K6: =Inventory_Master!N6 | L6: =IF(J6=0,0,MAX(J6,K6)) | M6: =Inventory_Master!K6 | N6: =Inventory_Master!L6 | O6: =L6*N6 | P6: =IF(L6>0,1,0) | Q6: =C6*Inventory_Master!D6*Cost_Assumptions!$B$4
A7: =Inventory_Master!A7 | B7: =Inventory_Master!B7 | C7: =Inventory_Master!E7 | D7: =Inventory_Master!F7 | E7: =Inventory_Master!G7 | F7: =Inventory_Master!H7 | G7: =Inventory_Master!I7 | H7: =IF(C7<=G7,"REORDER","OK") | I7: =D7*E7+F7+D7*Cost_Assumptions!$B$9 | J7: =MAX(0,I7-C7) | K7: =Inventory_Master!N7 | L7: =IF(J7=0,0,MAX(J7,K7)) | M7: =Inventory_Master!K7 | N7: =Inventory_Master!L7 | O7: =L7*N7 | P7: =IF(L7>0,1,0) | Q7: =C7*Inventory_Master!D7*Cost_Assumptions!$B$4
A8: =Inventory_Master!A8 | B8: =Inventory_Master!B8 | C8: =Inventory_Master!E8 | D8: =Inventory_Master!F8 | E8: =Inventory_Master!G8 | F8: =Inventory_Master!H8 | G8: =Inventory_Master!I8 | H8: =IF(C8<=G8,"REORDER","OK") | I8: =D8*E8+F8+D8*Cost_Assumptions!$B$9 | J8: =MAX(0,I8-C8) | K8: =Inventory_Master!N8 | L8: =IF(J8=0,0,MAX(J8,K8)) | M8: =Inventory_Master!K8 | N8: =Inventory_Master!L8 | O8: =L8*N8 | P8: =IF(L8>0,1,0) | Q8: =C8*Inventory_Master!D8*Cost_Assumptions!$B$4
A9: =Inventory_Master!A9 | B9: =Inventory_Master!B9 | C9: =Inventory_Master!E9 | D9: =Inventory_Master!F9 | E9: =Inventory_Master!G9 | F9: =Inventory_Master!H9 | G9: =Inventory_Master!I9 | H9: =IF(C9<=G9,"REORDER","OK") | I9: =D9*E9+F9+D9*Cost_Assumptions!$B$9 | J9: =MAX(0,I9-C9) | K9: =Inventory_Master!N9 | L9: =IF(J9=0,0,MAX(J9,K9)) | M9: =Inventory_Master!K9 | N9: =Inventory_Master!L9 | O9: =L9*N9 | P9: =IF(L9>0,1,0) | Q9: =C9*Inventory_Master!D9*Cost_Assumptions!$B$4
A10: =Inventory_Master!A10 | B10: =Inventory_Master!B10 | C10: =Inventory_Master!E10 | D10: =Inventory_Master!F10 | E10: =Inventory_Master!G10 | F10: =Inventory_Master!H10 | G10: =Inventory_Master!I10 | H10: =IF(C10<=G10,"REORDER","OK") | I10: =D10*E10+F10+D10*Cost_Assumptions!$B$9 | J10: =MAX(0,I10-C10) | K10: =Inventory_Master!N10 | L10: =IF(J10=0,0,MAX(J10,K10)) | M10: =Inventory_Master!K10 | N10: =Inventory_Master!L10 | O10: =L10*N10 | P10: =IF(L10>0,1,0) | Q10: =C10*Inventory_Master!D10*Cost_Assumptions!$B$4
A11: =Inventory_Master!A11 | B11: =Inventory_Master!B11 | C11: =Inventory_Master!E11 | D11: =Inventory_Master!F11 | E11: =Inventory_Master!G11 | F11: =Inventory_Master!H11 | G11: =Inventory_Master!I11 | H11: =IF(C11<=G11,"REORDER","OK") | I11: =D11*E11+F11+D11*Cost_Assumptions!$B$9 | J11: =MAX(0,I11-C11) | K11: =Inventory_Master!N11 | L11: =IF(J11=0,0,MAX(J11,K11)) | M11: =Inventory_Master!K11 | N11: =Inventory_Master!L11 | O11: =L11*N11 | P11: =IF(L11>0,1,0) | Q11: =C11*Inventory_Master!D11*Cost_Assumptions!$B$4
A12: =Inventory_Master!A12 | B12: =Inventory_Master!B12 | C12: =Inventory_Master!E12 | D12: =Inventory_Master!F12 | E12: =Inventory_Master!G12 | F12: =Inventory_Master!H12 | G12: =Inventory_Master!I12 | H12: =IF(C12<=G12,"REORDER","OK") | I12: =D12*E12+F12+D12*Cost_Assumptions!$B$9 | J12: =MAX(0,I12-C12) | K12: =Inventory_Master!N12 | L12: =IF(J12=0,0,MAX(J12,K12)) | M12: =Inventory_Master!K12 | N12: =Inventory_Master!L12 | O12: =L12*N12 | P12: =IF(L12>0,1,0) | Q12: =C12*Inventory_Master!D12*Cost_Assumptions!$B$4
A13: =Inventory_Master!A13 | B13: =Inventory_Master!B13 | C13: =Inventory_Master!E13 | D13: =Inventory_Master!F13 | E13: =Inventory_Master!G13 | F13: =Inventory_Master!H13 | G13: =Inventory_Master!I13 | H13: =IF(C13<=G13,"REORDER","OK") | I13: =D13*E13+F13+D13*Cost_Assumptions!$B$9 | J13: =MAX(0,I13-C13) | K13: =Inventory_Master!N13 | L13: =IF(J13=0,0,MAX(J13,K13)) | M13: =Inventory_Master!K13 | N13: =Inventory_Master!L13 | O13: =L13*N13 | P13: =IF(L13>0,1,0) | Q13: =C13*Inventory_Master!D13*Cost_Assumptions!$B$4
A14: =Inventory_Master!A14 | B14: =Inventory_Master!B14 | C14: =Inventory_Master!E14 | D14: =Inventory_Master!F14 | E14: =Inventory_Master!G14 | F14: =Inventory_Master!H14 | G14: =Inventory_Master!I14 | H14: =IF(C14<=G14,"REORDER","OK") | I14: =D14*E14+F14+D14*Cost_Assumptions!$B$9 | J14: =MAX(0,I14-C14) | K14: =Inventory_Master!N14 | L14: =IF(J14=0,0,MAX(J14,K14)) | M14: =Inventory_Master!K14 | N14: =Inventory_Master!L14 | O14: =L14*N14 | P14: =IF(L14>0,1,0) | Q14: =C14*Inventory_Master!D14*Cost_Assumptions!$B$4
A15: =Inventory_Master!A15 | B15: =Inventory_Master!B15 | C15: =Inventory_Master!E15 | D15: =Inventory_Master!F15 | E15: =Inventory_Master!G15 | F15: =Inventory_Master!H15 | G15: =Inventory_Master!I15 | H15: =IF(C15<=G15,"REORDER","OK") | I15: =D15*E15+F15+D15*Cost_Assumptions!$B$9 | J15: =MAX(0,I15-C15) | K15: =Inventory_Master!N15 | L15: =IF(J15=0,0,MAX(J15,K15)) | M15: =Inventory_Master!K15 | N15: =Inventory_Master!L15 | O15: =L15*N15 | P15: =IF(L15>0,1,0) | Q15: =C15*Inventory_Master!D15*Cost_Assumptions!$B$4
... A33: =Inventory_Master!A33 | B33: =Inventory_Master!B33 | C33: =Inventory_Master!E33 | D33: =Inventory_Master!F33 | E33: =Inventory_Master!G33 | F33: =Inventory_Master!H33 | G33: =Inventory_Master!I33 | H33: =IF(C33<=G33,"REORDER","OK") | I33: =D33*E33+F33+D33*Cost_Assumptions!$B$9 | J33: =MAX(0,I33-C33) | K33: =Inventory_Master!N33 | L33: =IF(J33=0,0,MAX(J33,K33)) | M33: =Inventory_Master!K33 | N33: =Inventory_Master!L33 | O33: =L33*N33 | P33: =IF(L33>0,1,0) | Q33: =C33*Inventory_Master!D33*Cost_Assumptions!$B$4

Sheet Scenario_Analysis
A1: Scenario Analysis
A2: Three scenarios per SKU. Suggested order quantity includes target stock cover and supplier MOQ.
A3: SKU | B3: Product | C3: Scenario | D3: Daily Demand | E3: Lead Time (days) | F3: Safety Stock | G3: Scenario Reorder Point | H3: Current Stock | I3: Gap to Reorder Point | J3: Target Stock | K3: Suggested Order Qty (MOQ-adjusted) | L3: Estimated Purchase Cost (₹)
A4: =Inventory_Master!A4 | B4: =Inventory_Master!B4 | C4: Baseline | D4: =Inventory_Master!F4 | E4: =Inventory_Master!G4 | F4: =Inventory_Master!H4 | G4: =D4*E4+F4 | H4: =Inventory_Master!E4 | I4: =MAX(0,G4-H4) | J4: =D4*E4+F4+D4*Cost_Assumptions!$B$9 | K4: =IF(J4<=H4,0,MAX(J4-H4,Inventory_Master!N4)) | L4: =K4*Inventory_Master!L4
A5: =Inventory_Master!A4 | B5: =Inventory_Master!B4 | C5: High Demand | D5: =Inventory_Master!F4*Cost_Assumptions!$B$7 | E5: =Inventory_Master!G4 | F5: =Inventory_Master!H4 | G5: =D5*E5+F5 | H5: =Inventory_Master!E4 | I5: =MAX(0,G5-H5) | J5: =D5*E5+F5+D5*Cost_Assumptions!$B$9 | K5: =IF(J5<=H5,0,MAX(J5-H5,Inventory_Master!N4)) | L5: =K5*Inventory_Master!L4
A6: =Inventory_Master!A4 | B6: =Inventory_Master!B4 | C6: Supplier Delay | D6: =Inventory_Master!F4 | E6: =Inventory_Master!G4+Cost_Assumptions!$B$8 | F6: =Inventory_Master!H4 | G6: =D6*E6+F6 | H6: =Inventory_Master!E4 | I6: =MAX(0,G6-H6) | J6: =D6*E6+F6+D6*Cost_Assumptions!$B$9 | K6: =IF(J6<=H6,0,MAX(J6-H6,Inventory_Master!N4)) | L6: =K6*Inventory_Master!L4
A7: =Inventory_Master!A5 | B7: =Inventory_Master!B5 | C7: Baseline | D7: =Inventory_Master!F5 | E7: =Inventory_Master!G5 | F7: =Inventory_Master!H5 | G7: =D7*E7+F7 | H7: =Inventory_Master!E5 | I7: =MAX(0,G7-H7) | J7: =D7*E7+F7+D7*Cost_Assumptions!$B$9 | K7: =IF(J7<=H7,0,MAX(J7-H7,Inventory_Master!N5)) | L7: =K7*Inventory_Master!L5
A8: =Inventory_Master!A5 | B8: =Inventory_Master!B5 | C8: High Demand | D8: =Inventory_Master!F5*Cost_Assumptions!$B$7 | E8: =Inventory_Master!G5 | F8: =Inventory_Master!H5 | G8: =D8*E8+F8 | H8: =Inventory_Master!E5 | I8: =MAX(0,G8-H8) | J8: =D8*E8+F8+D8*Cost_Assumptions!$B$9 | K8: =IF(J8<=H8,0,MAX(J8-H8,Inventory_Master!N5)) | L8: =K8*Inventory_Master!L5
A9: =Inventory_Master!A5 | B9: =Inventory_Master!B5 | C9: Supplier Delay | D9: =Inventory_Master!F5 | E9: =Inventory_Master!G5+Cost_Assumptions!$B$8 | F9: =Inventory_Master!H5 | G9: =D9*E9+F9 | H9: =Inventory_Master!E5 | I9: =MAX(0,G9-H9) | J9: =D9*E9+F9+D9*Cost_Assumptions!$B$9 | K9: =IF(J9<=H9,0,MAX(J9-H9,Inventory_Master!N5)) | L9: =K9*Inventory_Master!L5
A10: =Inventory_Master!A6 | B10: =Inventory_Master!B6 | C10: Baseline | D10: =Inventory_Master!F6 | E10: =Inventory_Master!G6 | F10: =Inventory_Master!H6 | G10: =D10*E10+F10 | H10: =Inventory_Master!E6 | I10: =MAX(0,G10-H10) | J10: =D10*E10+F10+D10*Cost_Assumptions!$B$9 | K10: =IF(J10<=H10,0,MAX(J10-H10,Inventory_Master!N6)) | L10: =K10*Inventory_Master!L6
A11: =Inventory_Master!A6 | B11: =Inventory_Master!B6 | C11: High Demand | D11: =Inventory_Master!F6*Cost_Assumptions!$B$7 | E11: =Inventory_Master!G6 | F11: =Inventory_Master!H6 | G11: =D11*E11+F11 | H11: =Inventory_Master!E6 | I11: =MAX(0,G11-H11) | J11: =D11*E11+F11+D11*Cost_Assumptions!$B$9 | K11: =IF(J11<=H11,0,MAX(J11-H11,Inventory_Master!N6)) | L11: =K11*Inventory_Master!L6
A12: =Inventory_Master!A6 | B12: =Inventory_Master!B6 | C12: Supplier Delay | D12: =Inventory_Master!F6 | E12: =Inventory_Master!G6+Cost_Assumptions!$B$8 | F12: =Inventory_Master!H6 | G12: =D12*E12+F12 | H12: =Inventory_Master!E6 | I12: =MAX(0,G12-H12) | J12: =D12*E12+F12+D12*Cost_Assumptions!$B$9 | K12: =IF(J12<=H12,0,MAX(J12-H12,Inventory_Master!N6)) | L12: =K12*Inventory_Master!L6
A13: =Inventory_Master!A7 | B13: =Inventory_Master!B7 | C13: Baseline | D13: =Inventory_Master!F7 | E13: =Inventory_Master!G7 | F13: =Inventory_Master!H7 | G13: =D13*E13+F13 | H13: =Inventory_Master!E7 | I13: =MAX(0,G13-H13) | J13: =D13*E13+F13+D13*Cost_Assumptions!$B$9 | K13: =IF(J13<=H13,0,MAX(J13-H13,Inventory_Master!N7)) | L13: =K13*Inventory_Master!L7
A14: =Inventory_Master!A7 | B14: =Inventory_Master!B7 | C14: High Demand | D14: =Inventory_Master!F7*Cost_Assumptions!$B$7 | E14: =Inventory_Master!G7 | F14: =Inventory_Master!H7 | G14: =D14*E14+F14 | H14: =Inventory_Master!E7 | I14: =MAX(0,G14-H14) | J14: =D14*E14+F14+D14*Cost_Assumptions!$B$9 | K14: =IF(J14<=H14,0,MAX(J14-H14,Inventory_Master!N7)) | L14: =K14*Inventory_Master!L7
A15: =Inventory_Master!A7 | B15: =Inventory_Master!B7 | C15: Supplier Delay | D15: =Inventory_Master!F7 | E15: =Inventory_Master!G7+Cost_Assumptions!$B$8 | F15: =Inventory_Master!H7 | G15: =D15*E15+F15 | H15: =Inventory_Master!E7 | I15: =MAX(0,G15-H15) | J15: =D15*E15+F15+D15*Cost_Assumptions!$B$9 | K15: =IF(J15<=H15,0,MAX(J15-H15,Inventory_Master!N7)) | L15: =K15*Inventory_Master!L7
A16: =Inventory_Master!A8 | B16: =Inventory_Master!B8 | C16: Baseline | D16: =Inventory_Master!F8 | E16: =Inventory_Master!G8 | F16: =Inventory_Master!H8 | G16: =D16*E16+F16 | H16: =Inventory_Master!E8 | I16: =MAX(0,G16-H16) | J16: =D16*E16+F16+D16*Cost_Assumptions!$B$9 | K16: =IF(J16<=H16,0,MAX(J16-H16,Inventory_Master!N8)) | L16: =K16*Inventory_Master!L8
A17: =Inventory_Master!A8 | B17: =Inventory_Master!B8 | C17: High Demand | D17: =Inventory_Master!F8*Cost_Assumptions!$B$7 | E17: =Inventory_Master!G8 | F17: =Inventory_Master!H8 | G17: =D17*E17+F17 | H17: =Inventory_Master!E8 | I17: =MAX(0,G17-H17) | J17: =D17*E17+F17+D17*Cost_Assumptions!$B$9 | K17: =IF(J17<=H17,0,MAX(J17-H17,Inventory_Master!N8)) | L17: =K17*Inventory_Master!L8
A18: =Inventory_Master!A8 | B18: =Inventory_Master!B8 | C18: Supplier Delay | D18: =Inventory_Master!F8 | E18: =Inventory_Master!G8+Cost_Assumptions!$B$8 | F18: =Inventory_Master!H8 | G18: =D18*E18+F18 | H18: =Inventory_Master!E8 | I18: =MAX(0,G18-H18) | J18: =D18*E18+F18+D18*Cost_Assumptions!$B$9 | K18: =IF(J18<=H18,0,MAX(J18-H18,Inventory_Master!N8)) | L18: =K18*Inventory_Master!L8
A19: =Inventory_Master!A9 | B19: =Inventory_Master!B9 | C19: Baseline | D19: =Inventory_Master!F9 | E19: =Inventory_Master!G9 | F19: =Inventory_Master!H9 | G19: =D19*E19+F19 | H19: =Inventory_Master!E9 | I19: =MAX(0,G19-H19) | J19: =D19*E19+F19+D19*Cost_Assumptions!$B$9 | K19: =IF(J19<=H19,0,MAX(J19-H19,Inventory_Master!N9)) | L19: =K19*Inventory_Master!L9
A20: =Inventory_Master!A9 | B20: =Inventory_Master!B9 | C20: High Demand | D20: =Inventory_Master!F9*Cost_Assumptions!$B$7 | E20: =Inventory_Master!G9 | F20: =Inventory_Master!H9 | G20: =D20*E20+F20 | H20: =Inventory_Master!E9 | I20: =MAX(0,G20-H20) | J20: =D20*E20+F20+D20*Cost_Assumptions!$B$9 | K20: =IF(J20<=H20,0,MAX(J20-H20,Inventory_Master!N9)) | L20: =K20*Inventory_Master!L9
A21: =Inventory_Master!A9 | B21: =Inventory_Master!B9 | C21: Supplier Delay | D21: =Inventory_Master!F9 | E21: =Inventory_Master!G9+Cost_Assumptions!$B$8 | F21: =Inventory_Master!H9 | G21: =D21*E21+F21 | H21: =Inventory_Master!E9 | I21: =MAX(0,G21-H21) | J21: =D21*E21+F21+D21*Cost_Assumptions!$B$9 | K21: =IF(J21<=H21,0,MAX(J21-H21,Inventory_Master!N9)) | L21: =K21*Inventory_Master!L9
A22: =Inventory_Master!A10 | B22: =Inventory_Master!B10 | C22: Baseline | D22: =Inventory_Master!F10 | E22: =Inventory_Master!G10 | F22: =Inventory_Master!H10 | G22: =D22*E22+F22 | H22: =Inventory_Master!E10 | I22: =MAX(0,G22-H22) | J22: =D22*E22+F22+D22*Cost_Assumptions!$B$9 | K22: =IF(J22<=H22,0,MAX(J22-H22,Inventory_Master!N10)) | L22: =K22*Inventory_Master!L10
A23: =Inventory_Master!A10 | B23: =Inventory_Master!B10 | C23: High Demand | D23: =Inventory_Master!F10*Cost_Assumptions!$B$7 | E23: =Inventory_Master!G10 | F23: =Inventory_Master!H10 | G23: =D23*E23+F23 | H23: =Inventory_Master!E10 | I23: =MAX(0,G23-H23) | J23: =D23*E23+F23+D23*Cost_Assumptions!$B$9 | K23: =IF(J23<=H23,0,MAX(J23-H23,Inventory_Master!N10)) | L23: =K23*Inventory_Master!L10
A24: =Inventory_Master!A10 | B24: =Inventory_Master!B10 | C24: Supplier Delay | D24: =Inventory_Master!F10 | E24: =Inventory_Master!G10+Cost_Assumptions!$B$8 | F24: =Inventory_Master!H10 | G24: =D24*E24+F24 | H24: =Inventory_Master!E10 | I24: =MAX(0,G24-H24) | J24: =D24*E24+F24+D24*Cost_Assumptions!$B$9 | K24: =IF(J24<=H24,0,MAX(J24-H24,Inventory_Master!N10)) | L24: =K24*Inventory_Master!L10
A25: =Inventory_Master!A11 | B25: =Inventory_Master!B11 | C25: Baseline | D25: =Inventory_Master!F11 | E25: =Inventory_Master!G11 | F25: =Inventory_Master!H11 | G25: =D25*E25+F25 | H25: =Inventory_Master!E11 | I25: =MAX(0,G25-H25) | J25: =D25*E25+F25+D25*Cost_Assumptions!$B$9 | K25: =IF(J25<=H25,0,MAX(J25-H25,Inventory_Master!N11)) | L25: =K25*Inventory_Master!L11
A26: =Inventory_Master!A11 | B26: =Inventory_Master!B11 | C26: High Demand | D26: =Inventory_Master!F11*Cost_Assumptions!$B$7 | E26: =Inventory_Master!G11 | F26: =Inventory_Master!H11 | G26: =D26*E26+F26 | H26: =Inventory_Master!E11 | I26: =MAX(0,G26-H26) | J26: =D26*E26+F26+D26*Cost_Assumptions!$B$9 | K26: =IF(J26<=H26,0,MAX(J26-H26,Inventory_Master!N11)) | L26: =K26*Inventory_Master!L11
A27: =Inventory_Master!A11 | B27: =Inventory_Master!B11 | C27: Supplier Delay | D27: =Inventory_Master!F11 | E27: =Inventory_Master!G11+Cost_Assumptions!$B$8 | F27: =Inventory_Master!H11 | G27: =D27*E27+F27 | H27: =Inventory_Master!E11 | I27: =MAX(0,G27-H27) | J27: =D27*E27+F27+D27*Cost_Assumptions!$B$9 | K27: =IF(J27<=H27,0,MAX(J27-H27,Inventory_Master!N11)) | L27: =K27*Inventory_Master!L11
A28: =Inventory_Master!A12 | B28: =Inventory_Master!B12 | C28: Baseline | D28: =Inventory_Master!F12 | E28: =Inventory_Master!G12 | F28: =Inventory_Master!H12 | G28: =D28*E28+F28 | H28: =Inventory_Master!E12 | I28: =MAX(0,G28-H28) | J28: =D28*E28+F28+D28*Cost_Assumptions!$B$9 | K28: =IF(J28<=H28,0,MAX(J28-H28,Inventory_Master!N12)) | L28: =K28*Inventory_Master!L12
A29: =Inventory_Master!A12 | B29: =Inventory_Master!B12 | C29: High Demand | D29: =Inventory_Master!F12*Cost_Assumptions!$B$7 | E29: =Inventory_Master!G12 | F29: =Inventory_Master!H12 | G29: =D29*E29+F29 | H29: =Inventory_Master!E12 | I29: =MAX(0,G29-H29) | J29: =D29*E29+F29+D29*Cost_Assumptions!$B$9 | K29: =IF(J29<=H29,0,MAX(J29-H29,Inventory_Master!N12)) | L29: =K29*Inventory_Master!L12
A30: =Inventory_Master!A12 | B30: =Inventory_Master!B12 | C30: Supplier Delay | D30: =Inventory_Master!F12 | E30: =Inventory_Master!G12+Cost_Assumptions!$B$8 | F30: =Inventory_Master!H12 | G30: =D30*E30+F30 | H30: =Inventory_Master!E12 | I30: =MAX(0,G30-H30) | J30: =D30*E30+F30+D30*Cost_Assumptions!$B$9 | K30: =IF(J30<=H30,0,MAX(J30-H30,Inventory_Master!N12)) | L30: =K30*Inventory_Master!L12
A31: =Inventory_Master!A13 | B31: =Inventory_Master!B13 | C31: Baseline | D31: =Inventory_Master!F13 | E31: =Inventory_Master!G13 | F31: =Inventory_Master!H13 | G31: =D31*E31+F31 | H31: =Inventory_Master!E13 | I31: =MAX(0,G31-H31) | J31: =D31*E31+F31+D31*Cost_Assumptions!$B$9 | K31: =IF(J31<=H31,0,MAX(J31-H31,Inventory_Master!N13)) | L31: =K31*Inventory_Master!L13
A32: =Inventory_Master!A13 | B32: =Inventory_Master!B13 | C32: High Demand | D32: =Inventory_Master!F13*Cost_Assumptions!$B$7 | E32: =Inventory_Master!G13 | F32: =Inventory_Master!H13 | G32: =D32*E32+F32 | H32: =Inventory_Master!E13 | I32: =MAX(0,G32-H32) | J32: =D32*E32+F32+D32*Cost_Assumptions!$B$9 | K32: =IF(J32<=H32,0,MAX(J32-H32,Inventory_Master!N13)) | L32: =K32*Inventory_Master!L13
A33: =Inventory_Master!A13 | B33: =Inventory_Master!B13 | C33: Supplier Delay | D33: =Inventory_Master!F13 | E33: =Inventory_Master!G13+Cost_Assumptions!$B$8 | F33: =Inventory_Master!H13 | G33: =D33*E33+F33 | H33: =Inventory_Master!E13 | I33: =MAX(0,G33-H33) | J33: =D33*E33+F33+D33*Cost_Assumptions!$B$9 | K33: =IF(J33<=H33,0,MAX(J33-H33,Inventory_Master!N13)) | L33: =K33*Inventory_Master!L13
A34: =Inventory_Master!A14 | B34: =Inventory_Master!B14 | C34: Baseline | D34: =Inventory_Master!F14 | E34: =Inventory_Master!G14 | F34: =Inventory_Master!H14 | G34: =D34*E34+F34 | H34: =Inventory_Master!E14 | I34: =MAX(0,G34-H34) | J34: =D34*E34+F34+D34*Cost_Assumptions!$B$9 | K34: =IF(J34<=H34,0,MAX(J34-H34,Inventory_Master!N14)) | L34: =K34*Inventory_Master!L14
A35: =Inventory_Master!A14 | B35: =Inventory_Master!B14 | C35: High Demand | D35: =Inventory_Master!F14*Cost_Assumptions!$B$7 | E35: =Inventory_Master!G14 | F35: =Inventory_Master!H14 | G35: =D35*E35+F35 | H35: =Inventory_Master!E14 | I35: =MAX(0,G35-H35) | J35: =D35*E35+F35+D35*Cost_Assumptions!$B$9 | K35: =IF(J35<=H35,0,MAX(J35-H35,Inventory_Master!N14)) | L35: =K35*Inventory_Master!L14
A36: =Inventory_Master!A14 | B36: =Inventory_Master!B14 | C36: Supplier Delay | D36: =Inventory_Master!F14 | E36: =Inventory_Master!G14+Cost_Assumptions!$B$8 | F36: =Inventory_Master!H14 | G36: =D36*E36+F36 | H36: =Inventory_Master!E14 | I36: =MAX(0,G36-H36) | J36: =D36*E36+F36+D36*Cost_Assumptions!$B$9 | K36: =IF(J36<=H36,0,MAX(J36-H36,Inventory_Master!N14)) | L36: =K36*Inventory_Master!L14
A37: =Inventory_Master!A15 | B37: =Inventory_Master!B15 | C37: Baseline | D37: =Inventory_Master!F15 | E37: =Inventory_Master!G15 | F37: =Inventory_Master!H15 | G37: =D37*E37+F37 | H37: =Inventory_Master!E15 | I37: =MAX(0,G37-H37) | J37: =D37*E37+F37+D37*Cost_Assumptions!$B$9 | K37: =IF(J37<=H37,0,MAX(J37-H37,Inventory_Master!N15)) | L37: =K37*Inventory_Master!L15
A38: =Inventory_Master!A15 | B38: =Inventory_Master!B15 | C38: High Demand | D38: =Inventory_Master!F15*Cost_Assumptions!$B$7 | E38: =Inventory_Master!G15 | F38: =Inventory_Master!H15 | G38: =D38*E38+F38 | H38: =Inventory_Master!E15 | I38: =MAX(0,G38-H38) | J38: =D38*E38+F38+D38*Cost_Assumptions!$B$9 | K38: =IF(J38<=H38,0,MAX(J38-H38,Inventory_Master!N15)) | L38: =K38*Inventory_Master!L15
A39: =Inventory_Master!A15 | B39: =Inventory_Master!B15 | C39: Supplier Delay | D39: =Inventory_Master!F15 | E39: =Inventory_Master!G15+Cost_Assumptions!$B$8 | F39: =Inventory_Master!H15 | G39: =D39*E39+F39 | H39: =Inventory_Master!E15 | I39: =MAX(0,G39-H39) | J39: =D39*E39+F39+D39*Cost_Assumptions!$B$9 | K39: =IF(J39<=H39,0,MAX(J39-H39,Inventory_Master!N15)) | L39: =K39*Inventory_Master!L15
A40: =Inventory_Master!A16 | B40: =Inventory_Master!B16 | C40: Baseline | D40: =Inventory_Master!F16 | E40: =Inventory_Master!G16 | F40: =Inventory_Master!H16 | G40: =D40*E40+F40 | H40: =Inventory_Master!E16 | I40: =MAX(0,G40-H40) | J40: =D40*E40+F40+D40*Cost_Assumptions!$B$9 | K40: =IF(J40<=H40,0,MAX(J40-H40,Inventory_Master!N16)) | L40: =K40*Inventory_Master!L16
A41: =Inventory_Master!A16 | B41: =Inventory_Master!B16 | C41: High Demand | D41: =Inventory_Master!F16*Cost_Assumptions!$B$7 | E41: =Inventory_Master!G16 | F41: =Inventory_Master!H16 | G41: =D41*E41+F41 | H41: =Inventory_Master!E16 | I41: =MAX(0,G41-H41) | J41: =D41*E41+F41+D41*Cost_Assumptions!$B$9 | K41: =IF(J41<=H41,0,MAX(J41-H41,Inventory_Master!N16)) | L41: =K41*Inventory_Master!L16
A42: =Inventory_Master!A16 | B42: =Inventory_Master!B16 | C42: Supplier Delay | D42: =Inventory_Master!F16 | E42: =Inventory_Master!G16+Cost_Assumptions!$B$8 | F42: =Inventory_Master!H16 | G42: =D42*E42+F42 | H42: =Inventory_Master!E16 | I42: =MAX(0,G42-H42) | J42: =D42*E42+F42+D42*Cost_Assumptions!$B$9 | K42: =IF(J42<=H42,0,MAX(J42-H42,Inventory_Master!N16)) | L42: =K42*Inventory_Master!L16
A43: =Inventory_Master!A17 | B43: =Inventory_Master!B17 | C43: Baseline | D43: =Inventory_Master!F17 | E43: =Inventory_Master!G17 | F43: =Inventory_Master!H17 | G43: =D43*E43+F43 | H43: =Inventory_Master!E17 | I43: =MAX(0,G43-H43) | J43: =D43*E43+F43+D43*Cost_Assumptions!$B$9 | K43: =IF(J43<=H43,0,MAX(J43-H43,Inventory_Master!N17)) | L43: =K43*Inventory_Master!L17
A44: =Inventory_Master!A17 | B44: =Inventory_Master!B17 | C44: High Demand | D44: =Inventory_Master!F17*Cost_Assumptions!$B$7 | E44: =Inventory_Master!G17 | F44: =Inventory_Master!H17 | G44: =D44*E44+F44 | H44: =Inventory_Master!E17 | I44: =MAX(0,G44-H44) | J44: =D44*E44+F44+D44*Cost_Assumptions!$B$9 | K44: =IF(J44<=H44,0,MAX(J44-H44,Inventory_Master!N17)) | L44: =K44*Inventory_Master!L17
A45: =Inventory_Master!A17 | B45: =Inventory_Master!B17 | C45: Supplier Delay | D45: =Inventory_Master!F17 | E45: =Inventory_Master!G17+Cost_Assumptions!$B$8 | F45: =Inventory_Master!H17 | G45: =D45*E45+F45 | H45: =Inventory_Master!E17 | I45: =MAX(0,G45-H45) | J45: =D45*E45+F45+D45*Cost_Assumptions!$B$9 | K45: =IF(J45<=H45,0,MAX(J45-H45,Inventory_Master!N17)) | L45: =K45*Inventory_Master!L17
A46: =Inventory_Master!A18 | B46: =Inventory_Master!B18 | C46: Baseline | D46: =Inventory_Master!F18 | E46: =Inventory_Master!G18 | F46: =Inventory_Master!H18 | G46: =D46*E46+F46 | H46: =Inventory_Master!E18 | I46: =MAX(0,G46-H46) | J46: =D46*E46+F46+D46*Cost_Assumptions!$B$9 | K46: =IF(J46<=H46,0,MAX(J46-H46,Inventory_Master!N18)) | L46: =K46*Inventory_Master!L18
A47: =Inventory_Master!A18 | B47: =Inventory_Master!B18 | C47: High Demand | D47: =Inventory_Master!F18*Cost_Assumptions!$B$7 | E47: =Inventory_Master!G18 | F47: =Inventory_Master!H18 | G47: =D47*E47+F47 | H47: =Inventory_Master!E18 | I47: =MAX(0,G47-H47) | J47: =D47*E47+F47+D47*Cost_Assumptions!$B$9 | K47: =IF(J47<=H47,0,MAX(J47-H47,Inventory_Master!N18)) | L47: =K47*Inventory_Master!L18
A48: =Inventory_Master!A18 | B48: =Inventory_Master!B18 | C48: Supplier Delay | D48: =Inventory_Master!F18 | E48: =Inventory_Master!G18+Cost_Assumptions!$B$8 | F48: =Inventory_Master!H18 | G48: =D48*E48+F48 | H48: =Inventory_Master!E18 | I48: =MAX(0,G48-H48) | J48: =D48*E48+F48+D48*Cost_Assumptions!$B$9 | K48: =IF(J48<=H48,0,MAX(J48-H48,Inventory_Master!N18)) | L48: =K48*Inventory_Master!L18
A49: =Inventory_Master!A19 | B49: =Inventory_Master!B19 | C49: Baseline | D49: =Inventory_Master!F19 | E49: =Inventory_Master!G19 | F49: =Inventory_Master!H19 | G49: =D49*E49+F49 | H49: =Inventory_Master!E19 | I49: =MAX(0,G49-H49) | J49: =D49*E49+F49+D49*Cost_Assumptions!$B$9 | K49: =IF(J49<=H49,0,MAX(J49-H49,Inventory_Master!N19)) | L49: =K49*Inventory_Master!L19
A50: =Inventory_Master!A19 | B50: =Inventory_Master!B19 | C50: High Demand | D50: =Inventory_Master!F19*Cost_Assumptions!$B$7 | E50: =Inventory_Master!G19 | F50: =Inventory_Master!H19 | G50: =D50*E50+F50 | H50: =Inventory_Master!E19 | I50: =MAX(0,G50-H50) | J50: =D50*E50+F50+D50*Cost_Assumptions!$B$9 | K50: =IF(J50<=H50,0,MAX(J50-H50,Inventory_Master!N19)) | L50: =K50*Inventory_Master!L19
A51: =Inventory_Master!A19 | B51: =Inventory_Master!B19 | C51: Supplier Delay | D51: =Inventory_Master!F19 | E51: =Inventory_Master!G19+Cost_Assumptions!$B$8 | F51: =Inventory_Master!H19 | G51: =D51*E51+F51 | H51: =Inventory_Master!E19 | I51: =MAX(0,G51-H51) | J51: =D51*E51+F51+D51*Cost_Assumptions!$B$9 | K51: =IF(J51<=H51,0,MAX(J51-H51,Inventory_Master!N19)) | L51: =K51*Inventory_Master!L19
A52: =Inventory_Master!A20 | B52: =Inventory_Master!B20 | C52: Baseline | D52: =Inventory_Master!F20 | E52: =Inventory_Master!G20 | F52: =Inventory_Master!H20 | G52: =D52*E52+F52 | H52: =Inventory_Master!E20 | I52: =MAX(0,G52-H52) | J52: =D52*E52+F52+D52*Cost_Assumptions!$B$9 | K52: =IF(J52<=H52,0,MAX(J52-H52,Inventory_Master!N20)) | L52: =K52*Inventory_Master!L20
A53: =Inventory_Master!A20 | B53: =Inventory_Master!B20 | C53: High Demand | D53: =Inventory_Master!F20*Cost_Assumptions!$B$7 | E53: =Inventory_Master!G20 | F53: =Inventory_Master!H20 | G53: =D53*E53+F53 | H53: =Inventory_Master!E20 | I53: =MAX(0,G53-H53) | J53: =D53*E53+F53+D53*Cost_Assumptions!$B$9 | K53: =IF(J53<=H53,0,MAX(J53-H53,Inventory_Master!N20)) | L53: =K53*Inventory_Master!L20
A54: =Inventory_Master!A20 | B54: =Inventory_Master!B20 | C54: Supplier Delay | D54: =Inventory_Master!F20 | E54: =Inventory_Master!G20+Cost_Assumptions!$B$8 | F54: =Inventory_Master!H20 | G54: =D54*E54+F54 | H54: =Inventory_Master!E20 | I54: =MAX(0,G54-H54) | J54: =D54*E54+F54+D54*Cost_Assumptions!$B$9 | K54: =IF(J54<=H54,0,MAX(J54-H54,Inventory_Master!N20)) | L54: =K54*Inventory_Master!L20
A55: =Inventory_Master!A21 | B55: =Inventory_Master!B21 | C55: Baseline | D55: =Inventory_Master!F21 | E55: =Inventory_Master!G21 | F55: =Inventory_Master!H21 | G55: =D55*E55+F55 | H55: =Inventory_Master!E21 | I55: =MAX(0,G55-H55) | J55: =D55*E55+F55+D55*Cost_Assumptions!$B$9 | K55: =IF(J55<=H55,0,MAX(J55-H55,Inventory_Master!N21)) | L55: =K55*Inventory_Master!L21
A56: =Inventory_Master!A21 | B56: =Inventory_Master!B21 | C56: High Demand | D56: =Inventory_Master!F21*Cost_Assumptions!$B$7 | E56: =Inventory_Master!G21 | F56: =Inventory_Master!H21 | G56: =D56*E56+F56 | H56: =Inventory_Master!E21 | I56: =MAX(0,G56-H56) | J56: =D56*E56+F56+D56*Cost_Assumptions!$B$9 | K56: =IF(J56<=H56,0,MAX(J56-H56,Inventory_Master!N21)) | L56: =K56*Inventory_Master!L21
A57: =Inventory_Master!A21 | B57: =Inventory_Master!B21 | C57: Supplier Delay | D57: =Inventory_Master!F21 | E57: =Inventory_Master!G21+Cost_Assumptions!$B$8 | F57: =Inventory_Master!H21 | G57: =D57*E57+F57 | H57: =Inventory_Master!E21 | I57: =MAX(0,G57-H57) | J57: =D57*E57+F57+D57*Cost_Assumptions!$B$9 | K57: =IF(J57<=H57,0,MAX(J57-H57,Inventory_Master!N21)) | L57: =K57*Inventory_Master!L21
A58: =Inventory_Master!A22 | B58: =Inventory_Master!B22 | C58: Baseline | D58: =Inventory_Master!F22 | E58: =Inventory_Master!G22 | F58: =Inventory_Master!H22 | G58: =D58*E58+F58 | H58: =Inventory_Master!E22 | I58: =MAX(0,G58-H58) | J58: =D58*E58+F58+D58*Cost_Assumptions!$B$9 | K58: =IF(J58<=H58,0,MAX(J58-H58,Inventory_Master!N22)) | L58: =K58*Inventory_Master!L22
A59: =Inventory_Master!A22 | B59: =Inventory_Master!B22 | C59: High Demand | D59: =Inventory_Master!F22*Cost_Assumptions!$B$7 | E59: =Inventory_Master!G22 | F59: =Inventory_Master!H22 | G59: =D59*E59+F59 | H59: =Inventory_Master!E22 | I59: =MAX(0,G59-H59) | J59: =D59*E59+F59+D59*Cost_Assumptions!$B$9 | K59: =IF(J59<=H59,0,MAX(J59-H59,Inventory_Master!N22)) | L59: =K59*Inventory_Master!L22
A60: =Inventory_Master!A22 | B60: =Inventory_Master!B22 | C60: Supplier Delay | D60: =Inventory_Master!F22 | E60: =Inventory_Master!G22+Cost_Assumptions!$B$8 | F60: =Inventory_Master!H22 | G60: =D60*E60+F60 | H60: =Inventory_Master!E22 | I60: =MAX(0,G60-H60) | J60: =D60*E60+F60+D60*Cost_Assumptions!$B$9 | K60: =IF(J60<=H60,0,MAX(J60-H60,Inventory_Master!N22)) | L60: =K60*Inventory_Master!L22
A61: =Inventory_Master!A23 | B61: =Inventory_Master!B23 | C61: Baseline | D61: =Inventory_Master!F23 | E61: =Inventory_Master!G23 | F61: =Inventory_Master!H23 | G61: =D61*E61+F61 | H61: =Inventory_Master!E23 | I61: =MAX(0,G61-H61) | J61: =D61*E61+F61+D61*Cost_Assumptions!$B$9 | K61: =IF(J61<=H61,0,MAX(J61-H61,Inventory_Master!N23)) | L61: =K61*Inventory_Master!L23
A62: =Inventory_Master!A23 | B62: =Inventory_Master!B23 | C62: High Demand | D62: =Inventory_Master!F23*Cost_Assumptions!$B$7 | E62: =Inventory_Master!G23 | F62: =Inventory_Master!H23 | G62: =D62*E62+F62 | H62: =Inventory_Master!E23 | I62: =MAX(0,G62-H62) | J62: =D62*E62+F62+D62*Cost_Assumptions!$B$9 | K62: =IF(J62<=H62,0,MAX(J62-H62,Inventory_Master!N23)) | L62: =K62*Inventory_Master!L23
A63: =Inventory_Master!A23 | B63: =Inventory_Master!B23 | C63: Supplier Delay | D63: =Inventory_Master!F23 | E63: =Inventory_Master!G23+Cost_Assumptions!$B$8 | F63: =Inventory_Master!H23 | G63: =D63*E63+F63 | H63: =Inventory_Master!E23 | I63: =MAX(0,G63-H63) | J63: =D63*E63+F63+D63*Cost_Assumptions!$B$9 | K63: =IF(J63<=H63,0,MAX(J63-H63,Inventory_Master!N23)) | L63: =K63*Inventory_Master!L23
A64: =Inventory_Master!A24 | B64: =Inventory_Master!B24 | C64: Baseline | D64: =Inventory_Master!F24 | E64: =Inventory_Master!G24 | F64: =Inventory_Master!H24 | G64: =D64*E64+F64 | H64: =Inventory_Master!E24 | I64: =MAX(0,G64-H64) | J64: =D64*E64+F64+D64*Cost_Assumptions!$B$9 | K64: =IF(J64<=H64,0,MAX(J64-H64,Inventory_Master!N24)) | L64: =K64*Inventory_Master!L24
A65: =Inventory_Master!A24 | B65: =Inventory_Master!B24 | C65: High Demand | D65: =Inventory_Master!F24*Cost_Assumptions!$B$7 | E65: =Inventory_Master!G24 | F65: =Inventory_Master!H24 | G65: =D65*E65+F65 | H65: =Inventory_Master!E24 | I65: =MAX(0,G65-H65) | J65: =D65*E65+F65+D65*Cost_Assumptions!$B$9 | K65: =IF(J65<=H65,0,MAX(J65-H65,Inventory_Master!N24)) | L65: =K65*Inventory_Master!L24
A66: =Inventory_Master!A24 | B66: =Inventory_Master!B24 | C66: Supplier Delay | D66: =Inventory_Master!F24 | E66: =Inventory_Master!G24+Cost_Assumptions!$B$8 | F66: =Inventory_Master!H24 | G66: =D66*E66+F66 | H66: =Inventory_Master!E24 | I66: =MAX(0,G66-H66) | J66: =D66*E66+F66+D66*Cost_Assumptions!$B$9 | K66: =IF(J66<=H66,0,MAX(J66-H66,Inventory_Master!N24)) | L66: =K66*Inventory_Master!L24
A67: =Inventory_Master!A25 | B67: =Inventory_Master!B25 | C67: Baseline | D67: =Inventory_Master!F25 | E67: =Inventory_Master!G25 | F67: =Inventory_Master!H25 | G67: =D67*E67+F67 | H67: =Inventory_Master!E25 | I67: =MAX(0,G67-H67) | J67: =D67*E67+F67+D67*Cost_Assumptions!$B$9 | K67: =IF(J67<=H67,0,MAX(J67-H67,Inventory_Master!N25)) | L67: =K67*Inventory_Master!L25
A68: =Inventory_Master!A25 | B68: =Inventory_Master!B25 | C68: High Demand | D68: =Inventory_Master!F25*Cost_Assumptions!$B$7 | E68: =Inventory_Master!G25 | F68: =Inventory_Master!H25 | G68: =D68*E68+F68 | H68: =Inventory_Master!E25 | I68: =MAX(0,G68-H68) | J68: =D68*E68+F68+D68*Cost_Assumptions!$B$9 | K68: =IF(J68<=H68,0,MAX(J68-H68,Inventory_Master!N25)) | L68: =K68*Inventory_Master!L25
A69: =Inventory_Master!A25 | B69: =Inventory_Master!B25 | C69: Supplier Delay | D69: =Inventory_Master!F25 | E69: =Inventory_Master!G25+Cost_Assumptions!$B$8 | F69: =Inventory_Master!H25 | G69: =D69*E69+F69 | H69: =Inventory_Master!E25 | I69: =MAX(0,G69-H69) | J69: =D69*E69+F69+D69*Cost_Assumptions!$B$9 | K69: =IF(J69<=H69,0,MAX(J69-H69,Inventory_Master!N25)) | L69: =K69*Inventory_Master!L25
A70: =Inventory_Master!A26 | B70: =Inventory_Master!B26 | C70: Baseline | D70: =Inventory_Master!F26 | E70: =Inventory_Master!G26 | F70: =Inventory_Master!H26 | G70: =D70*E70+F70 | H70: =Inventory_Master!E26 | I70: =MAX(0,G70-H70) | J70: =D70*E70+F70+D70*Cost_Assumptions!$B$9 | K70: =IF(J70<=H70,0,MAX(J70-H70,Inventory_Master!N26)) | L70: =K70*Inventory_Master!L26
A71: =Inventory_Master!A26 | B71: =Inventory_Master!B26 | C71: High Demand | D71: =Inventory_Master!F26*Cost_Assumptions!$B$7 | E71: =Inventory_Master!G26 | F71: =Inventory_Master!H26 | G71: =D71*E71+F71 | H71: =Inventory_Master!E26 | I71: =MAX(0,G71-H71) | J71: =D71*E71+F71+D71*Cost_Assumptions!$B$9 | K71: =IF(J71<=H71,0,MAX(J71-H71,Inventory_Master!N26)) | L71: =K71*Inventory_Master!L26
A72: =Inventory_Master!A26 | B72: =Inventory_Master!B26 | C72: Supplier Delay | D72: =Inventory_Master!F26 | E72: =Inventory_Master!G26+Cost_Assumptions!$B$8 | F72: =Inventory_Master!H26 | G72: =D72*E72+F72 | H72: =Inventory_Master!E26 | I72: =MAX(0,G72-H72) | J72: =D72*E72+F72+D72*Cost_Assumptions!$B$9 | K72: =IF(J72<=H72,0,MAX(J72-H72,Inventory_Master!N26)) | L72: =K72*Inventory_Master!L26
A73: =Inventory_Master!A27 | B73: =Inventory_Master!B27 | C73: Baseline | D73: =Inventory_Master!F27 | E73: =Inventory_Master!G27 | F73: =Inventory_Master!H27 | G73: =D73*E73+F73 | H73: =Inventory_Master!E27 | I73: =MAX(0,G73-H73) | J73: =D73*E73+F73+D73*Cost_Assumptions!$B$9 | K73: =IF(J73<=H73,0,MAX(J73-H73,Inventory_Master!N27)) | L73: =K73*Inventory_Master!L27
A74: =Inventory_Master!A27 | B74: =Inventory_Master!B27 | C74: High Demand | D74: =Inventory_Master!F27*Cost_Assumptions!$B$7 | E74: =Inventory_Master!G27 | F74: =Inventory_Master!H27 | G74: =D74*E74+F74 | H74: =Inventory_Master!E27 | I74: =MAX(0,G74-H74) | J74: =D74*E74+F74+D74*Cost_Assumptions!$B$9 | K74: =IF(J74<=H74,0,MAX(J74-H74,Inventory_Master!N27)) | L74: =K74*Inventory_Master!L27
A75: =Inventory_Master!A27 | B75: =Inventory_Master!B27 | C75: Supplier Delay | D75: =Inventory_Master!F27 | E75: =Inventory_Master!G27+Cost_Assumptions!$B$8 | F75: =Inventory_Master!H27 | G75: =D75*E75+F75 | H75: =Inventory_Master!E27 | I75: =MAX(0,G75-H75) | J75: =D75*E75+F75+D75*Cost_Assumptions!$B$9 | K75: =IF(J75<=H75,0,MAX(J75-H75,Inventory_Master!N27)) | L75: =K75*Inventory_Master!L27
A76: =Inventory_Master!A28 | B76: =Inventory_Master!B28 | C76: Baseline | D76: =Inventory_Master!F28 | E76: =Inventory_Master!G28 | F76: =Inventory_Master!H28 | G76: =D76*E76+F76 | H76: =Inventory_Master!E28 | I76: =MAX(0,G76-H76) | J76: =D76*E76+F76+D76*Cost_Assumptions!$B$9 | K76: =IF(J76<=H76,0,MAX(J76-H76,Inventory_Master!N28)) | L76: =K76*Inventory_Master!L28
A77: =Inventory_Master!A28 | B77: =Inventory_Master!B28 | C77: High Demand | D77: =Inventory_Master!F28*Cost_Assumptions!$B$7 | E77: =Inventory_Master!G28 | F77: =Inventory_Master!H28 | G77: =D77*E77+F77 | H77: =Inventory_Master!E28 | I77: =MAX(0,G77-H77) | J77: =D77*E77+F77+D77*Cost_Assumptions!$B$9 | K77: =IF(J77<=H77,0,MAX(J77-H77,Inventory_Master!N28)) | L77: =K77*Inventory_Master!L28
A78: =Inventory_Master!A28 | B78: =Inventory_Master!B28 | C78: Supplier Delay | D78: =Inventory_Master!F28 | E78: =Inventory_Master!G28+Cost_Assumptions!$B$8 | F78: =Inventory_Master!H28 | G78: =D78*E78+F78 | H78: =Inventory_Master!E28 | I78: =MAX(0,G78-H78) | J78: =D78*E78+F78+D78*Cost_Assumptions!$B$9 | K78: =IF(J78<=H78,0,MAX(J78-H78,Inventory_Master!N28)) | L78: =K78*Inventory_Master!L28
A79: =Inventory_Master!A29 | B79: =Inventory_Master!B29 | C79: Baseline | D79: =Inventory_Master!F29 | E79: =Inventory_Master!G29 | F79: =Inventory_Master!H29 | G79: =D79*E79+F79 | H79: =Inventory_Master!E29 | I79: =MAX(0,G79-H79) | J79: =D79*E79+F79+D79*Cost_Assumptions!$B$9 | K79: =IF(J79<=H79,0,MAX(J79-H79,Inventory_Master!N29)) | L79: =K79*Inventory_Master!L29
A80: =Inventory_Master!A29 | B80: =Inventory_Master!B29 | C80: High Demand | D80: =Inventory_Master!F29*Cost_Assumptions!$B$7 | E80: =Inventory_Master!G29 | F80: =Inventory_Master!H29 | G80: =D80*E80+F80 | H80: =Inventory_Master!E29 | I80: =MAX(0,G80-H80) | J80: =D80*E80+F80+D80*Cost_Assumptions!$B$9 | K80: =IF(J80<=H80,0,MAX(J80-H80,Inventory_Master!N29)) | L80: =K80*Inventory_Master!L29
A81: =Inventory_Master!A29 | B81: =Inventory_Master!B29 | C81: Supplier Delay | D81: =Inventory_Master!F29 | E81: =Inventory_Master!G29+Cost_Assumptions!$B$8 | F81: =Inventory_Master!H29 | G81: =D81*E81+F81 | H81: =Inventory_Master!E29 | I81: =MAX(0,G81-H81) | J81: =D81*E81+F81+D81*Cost_Assumptions!$B$9 | K81: =IF(J81<=H81,0,MAX(J81-H81,Inventory_Master!N29)) | L81: =K81*Inventory_Master!L29
A82: =Inventory_Master!A30 | B82: =Inventory_Master!B30 | C82: Baseline | D82: =Inventory_Master!F30 | E82: =Inventory_Master!G30 | F82: =Inventory_Master!H30 | G82: =D82*E82+F82 | H82: =Inventory_Master!E30 | I82: =MAX(0,G82-H82) | J82: =D82*E82+F82+D82*Cost_Assumptions!$B$9 | K82: =IF(J82<=H82,0,MAX(J82-H82,Inventory_Master!N30)) | L82: =K82*Inventory_Master!L30
A83: =Inventory_Master!A30 | B83: =Inventory_Master!B30 | C83: High Demand | D83: =Inventory_Master!F30*Cost_Assumptions!$B$7 | E83: =Inventory_Master!G30 | F83: =Inventory_Master!H30 | G83: =D83*E83+F83 | H83: =Inventory_Master!E30 | I83: =MAX(0,G83-H83) | J83: =D83*E83+F83+D83*Cost_Assumptions!$B$9 | K83: =IF(J83<=H83,0,MAX(J83-H83,Inventory_Master!N30)) | L83: =K83*Inventory_Master!L30
A84: =Inventory_Master!A30 | B84: =Inventory_Master!B30 | C84: Supplier Delay | D84: =Inventory_Master!F30 | E84: =Inventory_Master!G30+Cost_Assumptions!$B$8 | F84: =Inventory_Master!H30 | G84: =D84*E84+F84 | H84: =Inventory_Master!E30 | I84: =MAX(0,G84-H84) | J84: =D84*E84+F84+D84*Cost_Assumptions!$B$9 | K84: =IF(J84<=H84,0,MAX(J84-H84,Inventory_Master!N30)) | L84: =K84*Inventory_Master!L30
A85: =Inventory_Master!A31 | B85: =Inventory_Master!B31 | C85: Baseline | D85: =Inventory_Master!F31 | E85: =Inventory_Master!G31 | F85: =Inventory_Master!H31 | G85: =D85*E85+F85 | H85: =Inventory_Master!E31 | I85: =MAX(0,G85-H85) | J85: =D85*E85+F85+D85*Cost_Assumptions!$B$9 | K85: =IF(J85<=H85,0,MAX(J85-H85,Inventory_Master!N31)) | L85: =K85*Inventory_Master!L31
A86: =Inventory_Master!A31 | B86: =Inventory_Master!B31 | C86: High Demand | D86: =Inventory_Master!F31*Cost_Assumptions!$B$7 | E86: =Inventory_Master!G31 | F86: =Inventory_Master!H31 | G86: =D86*E86+F86 | H86: =Inventory_Master!E31 | I86: =MAX(0,G86-H86) | J86: =D86*E86+F86+D86*Cost_Assumptions!$B$9 | K86: =IF(J86<=H86,0,MAX(J86-H86,Inventory_Master!N31)) | L86: =K86*Inventory_Master!L31
A87: =Inventory_Master!A31 | B87: =Inventory_Master!B31 | C87: Supplier Delay | D87: =Inventory_Master!F31 | E87: =Inventory_Master!G31+Cost_Assumptions!$B$8 | F87: =Inventory_Master!H31 | G87: =D87*E87+F87 | H87: =Inventory_Master!E31 | I87: =MAX(0,G87-H87) | J87: =D87*E87+F87+D87*Cost_Assumptions!$B$9 | K87: =IF(J87<=H87,0,MAX(J87-H87,Inventory_Master!N31)) | L87: =K87*Inventory_Master!L31
A88: =Inventory_Master!A32 | B88: =Inventory_Master!B32 | C88: Baseline | D88: =Inventory_Master!F32 | E88: =Inventory_Master!G32 | F88: =Inventory_Master!H32 | G88: =D88*E88+F88 | H88: =Inventory_Master!E32 | I88: =MAX(0,G88-H88) | J88: =D88*E88+F88+D88*Cost_Assumptions!$B$9 | K88: =IF(J88<=H88,0,MAX(J88-H88,Inventory_Master!N32)) | L88: =K88*Inventory_Master!L32
A89: =Inventory_Master!A32 | B89: =Inventory_Master!B32 | C89: High Demand | D89: =Inventory_Master!F32*Cost_Assumptions!$B$7 | E89: =Inventory_Master!G32 | F89: =Inventory_Master!H32 | G89: =D89*E89+F89 | H89: =Inventory_Master!E32 | I89: =MAX(0,G89-H89) | J89: =D89*E89+F89+D89*Cost_Assumptions!$B$9 | K89: =IF(J89<=H89,0,MAX(J89-H89,Inventory_Master!N32)) | L89: =K89*Inventory_Master!L32
A90: =Inventory_Master!A32 | B90: =Inventory_Master!B32 | C90: Supplier Delay | D90: =Inventory_Master!F32 | E90: =Inventory_Master!G32+Cost_Assumptions!$B$8 | F90: =Inventory_Master!H32 | G90: =D90*E90+F90 | H90: =Inventory_Master!E32 | I90: =MAX(0,G90-H90) | J90: =D90*E90+F90+D90*Cost_Assumptions!$B$9 | K90: =IF(J90<=H90,0,MAX(J90-H90,Inventory_Master!N32)) | L90: =K90*Inventory_Master!L32
A91: =Inventory_Master!A33 | B91: =Inventory_Master!B33 | C91: Baseline | D91: =Inventory_Master!F33 | E91: =Inventory_Master!G33 | F91: =Inventory_Master!H33 | G91: =D91*E91+F91 | H91: =Inventory_Master!E33 | I91: =MAX(0,G91-H91) | J91: =D91*E91+F91+D91*Cost_Assumptions!$B$9 | K91: =IF(J91<=H91,0,MAX(J91-H91,Inventory_Master!N33)) | L91: =K91*Inventory_Master!L33
A92: =Inventory_Master!A33 | B92: =Inventory_Master!B33 | C92: High Demand | D92: =Inventory_Master!F33*Cost_Assumptions!$B$7 | E92: =Inventory_Master!G33 | F92: =Inventory_Master!H33 | G92: =D92*E92+F92 | H92: =Inventory_Master!E33 | I92: =MAX(0,G92-H92) | J92: =D92*E92+F92+D92*Cost_Assumptions!$B$9 | K92: =IF(J92<=H92,0,MAX(J92-H92,Inventory_Master!N33)) | L92: =K92*Inventory_Master!L33
A93: =Inventory_Master!A33 | B93: =Inventory_Master!B33 | C93: Supplier Delay | D93: =Inventory_Master!F33 | E93: =Inventory_Master!G33+Cost_Assumptions!$B$8 | F93: =Inventory_Master!H33 | G93: =D93*E93+F93 | H93: =Inventory_Master!E33 | I93: =MAX(0,G93-H93) | J93: =D93*E93+F93+D93*Cost_Assumptions!$B$9 | K93: =IF(J93<=H93,0,MAX(J93-H93,Inventory_Master!N33)) | L93: =K93*Inventory_Master!L33

Sheet Cost_Analysis
A1: Cost Analysis
A2: Estimated annual holding costs and modeled procurement costs; interpret as scenario estimates, not accounting actuals.
A3: SKU | B3: Product | C3: Current Inventory Value (₹) | D3: Suggested Order Qty | E3: Suggested Purchase Cost (₹) | F3: Annual Holding Cost (₹) | G3: Estimated Order Processing Cost (₹) | H3: Illustrative Stockout Risk Units | I3: Illustrative Stockout Risk Cost (₹)
A4: =Inventory_Master!A4 | B4: =Inventory_Master!B4 | C4: =Inventory_Master!J4 | D4: =Replenishment_Plan!L4 | E4: =Replenishment_Plan!O4 | F4: =C4*Cost_Assumptions!$B$4 | G4: =IF(D4>0,Cost_Assumptions!$B$5,0) | H4: =Replenishment_Plan!G4-Replenishment_Plan!C4 | I4: =MAX(0,H4)*Cost_Assumptions!$B$6
A5: =Inventory_Master!A5 | B5: =Inventory_Master!B5 | C5: =Inventory_Master!J5 | D5: =Replenishment_Plan!L5 | E5: =Replenishment_Plan!O5 | F5: =C5*Cost_Assumptions!$B$4 | G5: =IF(D5>0,Cost_Assumptions!$B$5,0) | H5: =Replenishment_Plan!G5-Replenishment_Plan!C5 | I5: =MAX(0,H5)*Cost_Assumptions!$B$6
A6: =Inventory_Master!A6 | B6: =Inventory_Master!B6 | C6: =Inventory_Master!J6 | D6: =Replenishment_Plan!L6 | E6: =Replenishment_Plan!O6 | F6: =C6*Cost_Assumptions!$B$4 | G6: =IF(D6>0,Cost_Assumptions!$B$5,0) | H6: =Replenishment_Plan!G6-Replenishment_Plan!C6 | I6: =MAX(0,H6)*Cost_Assumptions!$B$6
A7: =Inventory_Master!A7 | B7: =Inventory_Master!B7 | C7: =Inventory_Master!J7 | D7: =Replenishment_Plan!L7 | E7: =Replenishment_Plan!O7 | F7: =C7*Cost_Assumptions!$B$4 | G7: =IF(D7>0,Cost_Assumptions!$B$5,0) | H7: =Replenishment_Plan!G7-Replenishment_Plan!C7 | I7: =MAX(0,H7)*Cost_Assumptions!$B$6
A8: =Inventory_Master!A8 | B8: =Inventory_Master!B8 | C8: =Inventory_Master!J8 | D8: =Replenishment_Plan!L8 | E8: =Replenishment_Plan!O8 | F8: =C8*Cost_Assumptions!$B$4 | G8: =IF(D8>0,Cost_Assumptions!$B$5,0) | H8: =Replenishment_Plan!G8-Replenishment_Plan!C8 | I8: =MAX(0,H8)*Cost_Assumptions!$B$6
A9: =Inventory_Master!A9 | B9: =Inventory_Master!B9 | C9: =Inventory_Master!J9 | D9: =Replenishment_Plan!L9 | E9: =Replenishment_Plan!O9 | F9: =C9*Cost_Assumptions!$B$4 | G9: =IF(D9>0,Cost_Assumptions!$B$5,0) | H9: =Replenishment_Plan!G9-Replenishment_Plan!C9 | I9: =MAX(0,H9)*Cost_Assumptions!$B$6
A10: =Inventory_Master!A10 | B10: =Inventory_Master!B10 | C10: =Inventory_Master!J10 | D10: =Replenishment_Plan!L10 | E10: =Replenishment_Plan!O10 | F10: =C10*Cost_Assumptions!$B$4 | G10: =IF(D10>0,Cost_Assumptions!$B$5,0) | H10: =Replenishment_Plan!G10-Replenishment_Plan!C10 | I10: =MAX(0,H10)*Cost_Assumptions!$B$6
A11: =Inventory_Master!A11 | B11: =Inventory_Master!B11 | C11: =Inventory_Master!J11 | D11: =Replenishment_Plan!L11 | E11: =Replenishment_Plan!O11 | F11: =C11*Cost_Assumptions!$B$4 | G11: =IF(D11>0,Cost_Assumptions!$B$5,0) | H11: =Replenishment_Plan!G11-Replenishment_Plan!C11 | I11: =MAX(0,H11)*Cost_Assumptions!$B$6
A12: =Inventory_Master!A12 | B12: =Inventory_Master!B12 | C12: =Inventory_Master!J12 | D12: =Replenishment_Plan!L12 | E12: =Replenishment_Plan!O12 | F12: =C12*Cost_Assumptions!$B$4 | G12: =IF(D12>0,Cost_Assumptions!$B$5,0) | H12: =Replenishment_Plan!G12-Replenishment_Plan!C12 | I12: =MAX(0,H12)*Cost_Assumptions!$B$6
A13: =Inventory_Master!A13 | B13: =Inventory_Master!B13 | C13: =Inventory_Master!J13 | D13: =Replenishment_Plan!L13 | E13: =Replenishment_Plan!O13 | F13: =C13*Cost_Assumptions!$B$4 | G13: =IF(D13>0,Cost_Assumptions!$B$5,0) | H13: =Replenishment_Plan!G13-Replenishment_Plan!C13 | I13: =MAX(0,H13)*Cost_Assumptions!$B$6
A14: =Inventory_Master!A14 | B14: =Inventory_Master!B14 | C14: =Inventory_Master!J14 | D14: =Replenishment_Plan!L14 | E14: =Replenishment_Plan!O14 | F14: =C14*Cost_Assumptions!$B$4 | G14: =IF(D14>0,Cost_Assumptions!$B$5,0) | H14: =Replenishment_Plan!G14-Replenishment_Plan!C14 | I14: =MAX(0,H14)*Cost_Assumptions!$B$6
A15: =Inventory_Master!A15 | B15: =Inventory_Master!B15 | C15: =Inventory_Master!J15 | D15: =Replenishment_Plan!L15 | E15: =Replenishment_Plan!O15 | F15: =C15*Cost_Assumptions!$B$4 | G15: =IF(D15>0,Cost_Assumptions!$B$5,0) | H15: =Replenishment_Plan!G15-Replenishment_Plan!C15 | I15: =MAX(0,H15)*Cost_Assumptions!$B$6
... A33: =Inventory_Master!A33 | B33: =Inventory_Master!B33 | C33: =Inventory_Master!J33 | D33: =Replenishment_Plan!L33 | E33: =Replenishment_Plan!O33 | F33: =C33*Cost_Assumptions!$B$4 | G33: =IF(D33>0,Cost_Assumptions!$B$5,0) | H33: =Replenishment_Plan!G33-Replenishment_Plan!C33 | I33: =MAX(0,H33)*Cost_Assumptions!$B$6

Sheet Management_Dashboard
A1: Inventory & Procurement Dashboard
A2: Synthetic data | Review Excel-calculated values before writing final findings.
A4: KEY PERFORMANCE INDICATORS
A5: Total Inventory Value | B5: =SUM(Inventory_Master!J4:J33) | D5: Products to Reorder | E5: =COUNTIF(Replenishment_Plan!H4:H33,"REORDER") | G5: Suggested Purchase Cost | H5: =SUM(Replenishment_Plan!O4:O33)
A8: Total SKUs | B8: =COUNTA(Inventory_Master!A4:A33) | D8: Supplier Quotes | E8: =COUNTA(Supplier_Comparison!C4:C93) | G8: Annual Holding Cost | H8: =SUM(Cost_Analysis!F4:F33)
A11: Reorder Order Count | B11: =SUM(Replenishment_Plan!P4:P33) | D11: Estimated Order Processing Cost | E11: =SUM(Cost_Analysis!G4:G33) | G11: Illustrative Stockout Risk Cost | H11: =SUM(Cost_Analysis!I4:I33)
A15: Inventory Value by Category
A16: Category | B16: Inventory Value (₹)
A17: Electronics | B17: =SUMIF(Inventory_Master!$C$4:$C$33,A17,Inventory_Master!$J$4:$J$33)
A18: Home | B18: =SUMIF(Inventory_Master!$C$4:$C$33,A18,Inventory_Master!$J$4:$J$33)
A19: Lifestyle | B19: =SUMIF(Inventory_Master!$C$4:$C$33,A19,Inventory_Master!$J$4:$J$33)
A20: Stationery | B20: =SUMIF(Inventory_Master!$C$4:$C$33,A20,Inventory_Master!$J$4:$J$33)
A21: Fitness | B21: =SUMIF(Inventory_Master!$C$4:$C$33,A21,Inventory_Master!$J$4:$J$33)
A24: Replenishment Status
A25: Status | B25: Number of SKUs
A26: REORDER | B26: =COUNTIF(Replenishment_Plan!H4:H33,"REORDER")
A27: OK | B27: =COUNTIF(Replenishment_Plan!H4:H33,"OK")
A30: Questions for your written analysis
A31: 1. Which category has the highest inventory value?
A32: 2. Which SKUs are below the reorder point?
A33: 3. Do the highest-scoring suppliers also offer the lowest price?
A34: 4. How does high demand change suggested order quantities?
A35: 5. What are the trade-offs between low cost and fast delivery?
